Workbook

Sheet Summary
A1: 0580-Security Technology Salutation after eliminating Passenger Checking Roles | Rev 1: baseline schedule, cost loading and BOQ mapping
A3: Project number and name | B3: 0580-Security Technology Salutation after eliminating Passenger Checking Roles
A4: Source of cost | B4: Signed contract with ETECHS (1 November 2026): Annex 3 price table (Revised-02) and clause 15 payment milestones
A5: Contract price | B5: 62000000
A6: Project start (NTP milestone) | B6: 46327
A7: Contract term end (36 months) | B7: 47422
A8: Activities | B8: 591
A9: Tasks (2 resources each) | B9: 500
A10: Milestones | B10: 91
A11: Cost loaded in P6 (SAR) | B11: =BOQ_Mapping!N505
A12: Difference to contract price | B12: =B11-B5
A13: Progress points loaded | B13: =BOQ_Mapping!R505
A14: Working calendar | B14: Sunday to Thursday, 8 hours; KSA official holidays; Eid dates are estimates to be updated
A15: How to read | B15: Station_BOQ gives the BOQ value of each station; Payment_Milestones applies the contract payment conditions; BOQ_Mapping shows each activity cost; Distribution_Keys explains the keys; S_Curve shows cost against progress; Invoicing_Monthly lists every invoice by month, milestone and station.

Sheet Station_BOQ
A1: Annex 3 price table: BOQ value by station (SAR, excluding VAT)
A2: A1-A6 are priced per station. Shared packages (design, PM, FAT, spares, training, cloud) are priced per railway and allocated to stations pro rata to A1-A6 hardware value.
A4: Station | B4: Railway | C4: A1 CCTV | D4: A2 Video mgmt and wall | E4: A3 Access and intercom | F4: A4 UPS | G4: A5 Poles, cabinets, network | H4: A6 Civil works | I4: Hardware subtotal | J4: Design and engineering | K4: Project management | L4: FAT | M4: Commissioning spares | N4: Training | O4: Cloud (12 mo) | P4: Shared total | Q4: Station value | R4: Share of price
A5: Riyadh (Thumamah) (NRY) | B5: NSR | C5: 338989 | D5: 417141 | E5: 44085 | F5: 56211 | G5: 860619 | H5: 745743 | I5: =SUM(C5:H5) | J5: 82837.4 | K5: 744951.98 | L5: 34510.376 | M5: 66982.13 | N5: 6573.9871 | O5: 82141.898 | P5: =SUM(J5:O5) | Q5: =I5+P5 | R5: =Q5/Q$19
A6: Makkah (HMK) | B6: HHR | C6: 1650175 | D6: 552237 | E6: 44085 | F6: 110563 | G6: 2715976 | H6: 571639 | I6: =SUM(C6:H6) | J6: 337786.51 | K6: 3026065.7 | L6: 64944.147 | M6: 175360.16 | N6: 21649.327 | O6: 439615.13 | P6: =SUM(J6:O6) | Q6: =I6+P6 | R6: =Q6/Q$19
A7: Riyadh (Malaz) (ERY) | B7: EWR | C7: 276849 | D7: 350866 | E7: 44085 | F7: 50114 | G7: 548042 | H7: 701825 | I7: =SUM(C7:H7) | J7: 86494.688 | K7: 779124.28 | L7: 56538.427 | M7: 106509.2 | N7: 18847.255 | O7: 72225.509 | P7: =SUM(J7:O7) | Q7: =I7+P7 | R7: =Q7/Q$19
A8: Jeddah (HJD) | B8: HHR | C8: 1391206 | D8: 652091 | E8: 44085 | F8: 102666 | G8: 2840354 | H8: 521718 | I8: =SUM(C8:H8) | J8: 332247.87 | K8: 2976447.7 | L8: 63879.266 | M8: 172484.8 | N8: 21294.346 | O8: 432406.82 | P8: =SUM(J8:O8) | Q8: =I8+P8 | R8: =Q8/Q$19
A9: Dammam (EDM) | B9: EWR | C9: 276849 | D9: 412102 | E9: 44085 | F9: 50114 | G9: 548042 | H9: 701813 | I9: =SUM(C9:H9) | J9: 89180.357 | K9: 803316.17 | L9: 58293.95 | M9: 109816.32 | N9: 19432.464 | O9: 74468.119 | P9: =SUM(J9:O9) | Q9: =I9+P9 | R9: =Q9/Q$19
A10: Al Qassim (NQS) | B10: NSR | C10: 338989 | D10: 359215 | E10: 44085 | F10: 56211 | G10: 860619 | H10: 745743 | I10: =SUM(C10:H10) | J10: 80889.023 | K10: 727430.34 | L10: 33698.675 | M10: 65406.677 | N10: 6419.3637 | O10: 80209.88 | P10: =SUM(J10:O10) | Q10: =I10+P10 | R10: =Q10/Q$19
A11: Hufuf (EHF) | B11: EWR | C11: 192155 | D11: 349033 | E11: 44085 | F11: 50114 | G11: 508774 | H11: 659866 | I11: =SUM(C11:H11) | J11: 79135.945 | K11: 712838.41 | L11: 51728.284 | M11: 97447.677 | N11: 17243.779 | O11: 66080.751 | P11: =SUM(J11:O11) | Q11: =I11+P11 | R11: =Q11/Q$19
A12: Al Majma'ah (NMJ) | B12: NSR | C12: 338989 | D12: 359215 | E12: 44085 | F12: 56211 | G12: 860619 | H12: 745743 | I12: =SUM(C12:H12) | J12: 80889.023 | K12: 727430.34 | L12: 33698.675 | M12: 65406.677 | N12: 6419.3637 | O12: 80209.88 | P12: =SUM(J12:O12) | Q12: =I12+P12 | R12: =Q12/Q$19
A13: KAEC (HKA) | B13: HHR | C13: 962039 | D13: 406364 | E13: 44085 | F13: 82168 | G13: 1552977 | H13: 187054 | I13: =SUM(C13:H13) | J13: 193568.92 | K13: 1734090.2 | L13: 37216.312 | M13: 100490.32 | N13: 12406.17 | O13: 251921.92 | P13: =SUM(J13:O13) | Q13: =I13+P13 | R13: =Q13/Q$19
A14: Madinah (HMD) | B14: HHR | C14: 934319 | D14: 409184 | E14: 44085 | F14: 74329 | G14: 1480427 | H14: 291036 | I14: =SUM(C14:H14) | J14: 193490.7 | K14: 1733389.5 | L14: 37201.275 | M14: 100449.72 | N14: 12401.157 | O14: 251820.13 | P14: =SUM(J14:O14) | Q14: =I14+P14 | R14: =Q14/Q$19
A15: Abqaiq (EAB) | B15: EWR | C15: 111083 | D15: 286032 | E15: 44085 | F15: 50114 | G15: 411979 | H15: 375936 | I15: =SUM(C15:H15) | J15: 56115.011 | K15: 505471.13 | L15: 36680.339 | M15: 69099.794 | N15: 12227.501 | O15: 46857.621 | P15: =SUM(J15:O15) | Q15: =I15+P15 | R15: =Q15/Q$19
A16: Hail (NHL) | B16: NSR | C16: 338989 | D16: 359215 | E16: 44085 | F16: 56211 | G16: 860619 | H16: 745743 | I16: =SUM(C16:H16) | J16: 80889.023 | K16: 727430.34 | L16: 33698.675 | M16: 65406.677 | N16: 6419.3637 | O16: 80209.88 | P16: =SUM(J16:O16) | Q16: =I16+P16 | R16: =Q16/Q$19
... A18: Al Qurayyat (NQR) | B18: NSR | C18: 338989 | D18: 359215 | E18: 44085 | F18: 56211 | G18: 860619 | H18: 745743 | I18: =SUM(C18:H18) | J18: 80889.023 | K18: 727430.34 | L18: 33698.675 | M18: 65406.677 | N18: 6419.3637 | O18: 80209.88 | P18: =SUM(J18:O18) | Q18: =I18+P18 | R18: =Q18/Q$19
A19: Total | C19: =SUM(C5:C18) | D19: =SUM(D5:D18) | E19: =SUM(E5:E18) | F19: =SUM(F5:F18) | G19: =SUM(G5:G18) | H19: =SUM(H5:H18) | I19: =SUM(I5:I18) | J19: =SUM(J5:J18) | ... R19: =SUM(R5:R18)
A21: Contract price (Annex 3) | C21: 62000000
A22: Difference (should be zero within SAR 5) | C22: =Q19-C21

Sheet Payment_Milestones
A1: Contract clause 15 payment milestones applied to each station price
A2: MS1 Mobilization is 20% of the TOTAL price. MS2 to MS7 are prorated per station on the station share of the price.
A4: Milestone | B4: Description | C4: Share of price | D4: Amount (SAR)
A5: MS1 | B5: Mobilization | C5: 0.2 | D5: =C5*62000000
A6: MS2 | B6: Engineering submittal | C6: 0.1 | D6: =C6*62000000
A7: MS3 | B7: SAR approval of engineering | C7: 0.1 | D7: =C7*62000000
A8: MS4 | B8: Material delivery | C8: 0.2 | D8: =C8*62000000
A9: MS5 | B9: Installation | C9: 0.2 | D9: =C9*62000000
A10: MS6 | B10: Testing and commissioning (SAT) | C10: 0.1 | D10: =C10*62000000
A11: MS7 | B11: Final acceptance and handover | C11: 0.1 | D11: =C11*62000000
A12: Total | C12: =SUM(C5:C11) | D12: =SUM(D5:D11)
A15: Station | B15: Station share | C15: MS2 amount | D15: MS3 amount | E15: MS4 amount | F15: MS5 amount | G15: MS6 amount | H15: MS7 amount | I15: Stations total MS2-MS7
A16: Riyadh (Thumamah) (NRY) | B16: =Station_BOQ!R5 | C16: =$B16*62000000*$C$6 | D16: =$B16*62000000*$C$7 | E16: =$B16*62000000*$C$8 | F16: =$B16*62000000*$C$9 | G16: =$B16*62000000*$C$10 | H16: =$B16*62000000*$C$11 | I16: =SUM(C16:H16)
A17: Makkah (HMK) | B17: =Station_BOQ!R6 | C17: =$B17*62000000*$C$6 | D17: =$B17*62000000*$C$7 | E17: =$B17*62000000*$C$8 | F17: =$B17*62000000*$C$9 | G17: =$B17*62000000*$C$10 | H17: =$B17*62000000*$C$11 | I17: =SUM(C17:H17)
A18: Riyadh (Malaz) (ERY) | B18: =Station_BOQ!R7 | C18: =$B18*62000000*$C$6 | D18: =$B18*62000000*$C$7 | E18: =$B18*62000000*$C$8 | F18: =$B18*62000000*$C$9 | G18: =$B18*62000000*$C$10 | H18: =$B18*62000000*$C$11 | I18: =SUM(C18:H18)
A19: Jeddah (HJD) | B19: =Station_BOQ!R8 | C19: =$B19*62000000*$C$6 | D19: =$B19*62000000*$C$7 | E19: =$B19*62000000*$C$8 | F19: =$B19*62000000*$C$9 | G19: =$B19*62000000*$C$10 | H19: =$B19*62000000*$C$11 | I19: =SUM(C19:H19)
A20: Dammam (EDM) | B20: =Station_BOQ!R9 | C20: =$B20*62000000*$C$6 | D20: =$B20*62000000*$C$7 | E20: =$B20*62000000*$C$8 | F20: =$B20*62000000*$C$9 | G20: =$B20*62000000*$C$10 | H20: =$B20*62000000*$C$11 | I20: =SUM(C20:H20)
A21: Al Qassim (NQS) | B21: =Station_BOQ!R10 | C21: =$B21*62000000*$C$6 | D21: =$B21*62000000*$C$7 | E21: =$B21*62000000*$C$8 | F21: =$B21*62000000*$C$9 | G21: =$B21*62000000*$C$10 | H21: =$B21*62000000*$C$11 | I21: =SUM(C21:H21)
A22: Hufuf (EHF) | B22: =Station_BOQ!R11 | C22: =$B22*62000000*$C$6 | D22: =$B22*62000000*$C$7 | E22: =$B22*62000000*$C$8 | F22: =$B22*62000000*$C$9 | G22: =$B22*62000000*$C$10 | H22: =$B22*62000000*$C$11 | I22: =SUM(C22:H22)
A23: Al Majma'ah (NMJ) | B23: =Station_BOQ!R12 | C23: =$B23*62000000*$C$6 | D23: =$B23*62000000*$C$7 | E23: =$B23*62000000*$C$8 | F23: =$B23*62000000*$C$9 | G23: =$B23*62000000*$C$10 | H23: =$B23*62000000*$C$11 | I23: =SUM(C23:H23)
A24: KAEC (HKA) | B24: =Station_BOQ!R13 | C24: =$B24*62000000*$C$6 | D24: =$B24*62000000*$C$7 | E24: =$B24*62000000*$C$8 | F24: =$B24*62000000*$C$9 | G24: =$B24*62000000*$C$10 | H24: =$B24*62000000*$C$11 | I24: =SUM(C24:H24)
A25: Madinah (HMD) | B25: =Station_BOQ!R14 | C25: =$B25*62000000*$C$6 | D25: =$B25*62000000*$C$7 | E25: =$B25*62000000*$C$8 | F25: =$B25*62000000*$C$9 | G25: =$B25*62000000*$C$10 | H25: =$B25*62000000*$C$11 | I25: =SUM(C25:H25)
A26: Abqaiq (EAB) | B26: =Station_BOQ!R15 | C26: =$B26*62000000*$C$6 | D26: =$B26*62000000*$C$7 | E26: =$B26*62000000*$C$8 | F26: =$B26*62000000*$C$9 | G26: =$B26*62000000*$C$10 | H26: =$B26*62000000*$C$11 | I26: =SUM(C26:H26)
A27: Hail (NHL) | B27: =Station_BOQ!R16 | C27: =$B27*62000000*$C$6 | D27: =$B27*62000000*$C$7 | E27: =$B27*62000000*$C$8 | F27: =$B27*62000000*$C$9 | G27: =$B27*62000000*$C$10 | H27: =$B27*62000000*$C$11 | I27: =SUM(C27:H27)
... A29: Al Qurayyat (NQR) | B29: =Station_BOQ!R18 | C29: =$B29*62000000*$C$6 | D29: =$B29*62000000*$C$7 | E29: =$B29*62000000*$C$8 | F29: =$B29*62000000*$C$9 | G29: =$B29*62000000*$C$10 | H29: =$B29*62000000*$C$11 | I29: =SUM(C29:H29)
A30: Total | B30: =SUM(B16:B29) | C30: =SUM(C16:C29) | D30: =SUM(D16:D29) | E30: =SUM(E16:E29) | F30: =SUM(F16:F29) | G30: =SUM(G16:G29) | H30: =SUM(H16:H29) | I30: =SUM(I16:I29)
A32: Check: MS1 + stations MS2-MS7 = total price | D32: =D5+I30

Sheet BOQ_Mapping
A1: Activity cost mapping: how each activity cost was distributed from the BOQ
A2: BOQ ID uses the Annex 3 section codes A1 to A6; the shared per-railway packages carry derived IDs SH-xx. Cost = milestone amount (payment condition x station share of the BOQ) x distribution key. Column M recomputes it with formulas; column N is the whole-riyal value loaded in P6.
A4: BOQ ID | B4: BOQ Description | C4: Activity ID | D4: Activity name | E4: WBS | F4: EPC phase | G4: Station | H4: Payment milestone | I4: Milestone % | J4: Station price share | K4: Milestone amount (SAR) | L4: Distribution key | M4: Cost recomputed | N4: Cost in P6 (SAR) | O4: Difference | P4: Distribution basis | Q4: Primary BOQ source | R4: Progress points | S4: Progress % of project | T4: Start | U4: Finish | V4: Duration (work days)
A5: TOTAL | B5: Contract price (Annex 3 total, SAR 62,000,000): 20% mobilization payment, clause 15 | C5: PRJ-A1010 | D5: Performance security, insurance and key personnel approval | E5: PM.MOB | F5: Mobilization | G5: PRJ | H5: MS1 | I5: 0.2 | K5: =Payment_Milestones!D5 | L5: 0.15 | M5: =ROUND(K5*L5,0) | N5: 1859999 | O5: =N5-M5 | P5: MS1 Mobilization 20% of the total price (SAR 12,400,000) x key 15% | Q5: Contract price (62,000,000) x 20% mobilization payment (contract clause 15) | R5: 400 | S5: =R5/1000 | T5: 46327 | U5: 46338 | V5: 10
A6: TOTAL | B6: Contract price (Annex 3 total, SAR 62,000,000): 20% mobilization payment, clause 15 | C6: PRJ-A1020 | D6: Initial baseline programme (Primavera) covering mobilization and survey | E6: PM.MOB | F6: Mobilization | G6: PRJ | H6: MS1 | I6: 0.2 | K6: =Payment_Milestones!D5 | L6: 0.1 | M6: =ROUND(K6*L6,0) | N6: 1239999 | O6: =N6-M6 | P6: MS1 Mobilization 20% of the total price (SAR 12,400,000) x key 10% | Q6: Contract price (62,000,000) x 20% mobilization payment (contract clause 15) | R6: 200 | S6: =R6/1000 | T6: 46327 | U6: 46335 | V6: 7
A7: - | B7: No BOQ cost: administrative or review step with no payment milestone | C7: PRJ-A1030 | D7: SAR review and approval of initial baseline | E7: PM.MOB | F7: Mobilization | G7: PRJ | I7: 0 | K7: 0 | L7: 0 | M7: 0 | N7: 0 | O7: =N7-M7 | P7: No payment milestone attached (administrative approval or review step) | Q7: - | R7: 200 | S7: =R7/1000 | T7: 46336 | U7: 46356 | V7: 15
A8: TOTAL | B8: Contract price (Annex 3 total, SAR 62,000,000): 20% mobilization payment, clause 15 | C8: PRJ-A1040 | D8: Mobilization: site establishment, offices, personnel and tools | E8: PM.MOB | F8: Mobilization | G8: PRJ | H8: MS1 | I8: 0.2 | K8: =Payment_Milestones!D5 | L8: 0.45 | M8: =ROUND(K8*L8,0) | N8: 5579999 | O8: =N8-M8 | P8: MS1 Mobilization 20% of the total price (SAR 12,400,000) x key 45% | Q8: Contract price (62,000,000) x 20% mobilization payment (contract clause 15) | R8: 700 | S8: =R8/1000 | T8: 46334 | U8: 46366 | V8: 25
A9: TOTAL | B9: Contract price (Annex 3 total, SAR 62,000,000): 20% mobilization payment, clause 15 | C9: PRJ-A1050 | D9: Mobilization submittals: QC programme and ITP, HSE, security, procurement and shipping plan | E9: PM.MOB | F9: Mobilization | G9: PRJ | H9: MS1 | I9: 0.2 | K9: =Payment_Milestones!D5 | L9: 0.3 | M9: =ROUND(K9*L9,0) | N9: 3719999 | O9: =N9-M9 | P9: MS1 Mobilization 20% of the total price (SAR 12,400,000) x key 30% | Q9: Contract price (62,000,000) x 20% mobilization payment (contract clause 15) | R9: 600 | S9: =R9/1000 | T9: 46334 | U9: 46359 | V9: 20
A10: - | B10: No BOQ cost: administrative or review step with no payment milestone | C10: PRJ-A1060 | D10: Site access permits for the surveys of all stations: application and approval (two months) | E10: PM.MOB | F10: Mobilization | G10: PRJ | I10: 0 | K10: 0 | L10: 0 | M10: 0 | N10: 0 | O10: =N10-M10 | P10: No payment milestone attached (administrative approval or review step) | Q10: - | R10: 100 | S10: =R10/1000 | T10: 46327 | U10: 46387 | V10: 45
A11: - | B11: No BOQ cost: administrative or review step with no payment milestone | C11: PRJ-A2010 | D11: Detailed baseline programme (after mobilization) | E11: PM.MOB | F11: Project management | G11: PRJ | I11: 0 | K11: 0 | L11: 0 | M11: 0 | N11: 0 | O11: =N11-M11 | P11: No payment milestone attached (administrative approval or review step) | Q11: - | R11: 300 | S11: =R11/1000 | T11: 46390 | U11: 46408 | V11: 15
A12: - | B12: No BOQ cost: administrative or review step with no payment milestone | C12: PRJ-A2020 | D12: SAR review and approval of detailed baseline | E12: PM.MOB | F12: Project management | G12: PRJ | I12: 0 | K12: 0 | L12: 0 | M12: 0 | N12: 0 | O12: =N12-M12 | P12: No payment milestone attached (administrative approval or review step) | Q12: - | R12: 200 | S12: =R12/1000 | T12: 46411 | U12: 46429 | V12: 15
A13: - | B13: No BOQ cost: administrative or review step with no payment milestone | C13: PRJ-C1010 | D13: Contract closeout pack and handover documentation | E13: PM.CLO | F13: Project management | G13: PRJ | I13: 0 | K13: 0 | L13: 0 | M13: 0 | N13: 0 | O13: =N13-M13 | P13: No payment milestone attached (administrative approval or review step) | Q13: - | R13: 1301 | S13: =R13/1000 | T13: 47374 | U13: 47388 | V13: 10
A14: SH-DES | B14: Design and engineering package (per railway, allocated to the station) | C14: NRY-E1010 | D14: Survey: submittal of site survey and as-found report - Riyadh (Thumamah) | E14: ENG.NRY.SRV.SUB | F14: Engineering | G14: NRY | H14: MS2 | I14: 0.1 | J14: =Station_BOQ!R5 | K14: =I14*62000000*J14 | L14: 0.069 | M14: =ROUND(K14*L14,0) | N14: 24017 | O14: =N14-M14 | P14: MS2 Engineering submittal 10% x station price share 5.61% | Design stage key 6.9% of the engineering-submittal milestone | Q14: Annex 3 Design and engineering package (railway) allocated by station hardware share | R14: 31 | S14: =R14/1000 | T14: 46390 | U14: 46399 | V14: 8
A15: SH-DES | B15: Design and engineering package (per railway, allocated to the station) | C15: NRY-E1020 | D15: Survey: SAR approval of survey report - Riyadh (Thumamah) | E15: ENG.NRY.SRV.APR | F15: Engineering | G15: NRY | H15: MS3 | I15: 0.1 | J15: =Station_BOQ!R5 | K15: =I15*62000000*J15 | L15: 0.05 | M15: =ROUND(K15*L15,0) | N15: 17404 | O15: =N15-M15 | P15: MS3 SAR approval of engineering 10% x station price share 5.61% | Design stage key 5.0% of the SAR-approval milestone | Q15: Annex 3 Design and engineering package (railway) allocated by station hardware share | R15: 33 | S15: =R15/1000 | T15: 46400 | U15: 46420 | V15: 15
A16: SH-DES | B16: Design and engineering package (per railway, allocated to the station) | C16: NRY-E1030 | D16: Concept design: submittal - Riyadh (Thumamah) | E16: ENG.NRY.CNC.SUB | F16: Engineering | G16: NRY | H16: MS2 | I16: 0.1 | J16: =Station_BOQ!R5 | K16: =I16*62000000*J16 | L16: 0.098 | M16: =ROUND(K16*L16,0) | N16: 34112 | O16: =N16-M16 | P16: MS2 Engineering submittal 10% x station price share 5.61% | Design stage key 9.8% of the engineering-submittal milestone | Q16: Annex 3 Design and engineering package (railway) allocated by station hardware share | R16: 22 | S16: =R16/1000 | T16: 46400 | U16: 46411 | V16: 8
A17: SH-DES | B17: Design and engineering package (per railway, allocated to the station) | C17: NRY-E1040 | D17: Concept design: SAR review and approval - Riyadh (Thumamah) | E17: ENG.NRY.CNC.APR | F17: Engineering | G17: NRY | H17: MS3 | I17: 0.1 | J17: =Station_BOQ!R5 | K17: =I17*62000000*J17 | L17: 0.1 | M17: =ROUND(K17*L17,0) | N17: 34808 | O17: =N17-M17 | P17: MS3 SAR approval of engineering 10% x station price share 5.61% | Design stage key 10.0% of the SAR-approval milestone | Q17: Annex 3 Design and engineering package (railway) allocated by station hardware share | R17: 41 | S17: =R17/1000 | T17: 46412 | U17: 46432 | V17: 15
A18: SH-DES | B18: Design and engineering package (per railway, allocated to the station) | C18: NRY-E1050 | D18: Preliminary design: submittal - Riyadh (Thumamah) | E18: ENG.NRY.PRE.SUB | F18: Engineering | G18: NRY | H18: MS2 | I18: 0.1 | J18: =Station_BOQ!R5 | K18: =I18*62000000*J18 | L18: 0.196 | M18: =ROUND(K18*L18,0) | N18: 68223 | O18: =N18-M18 | P18: MS2 Engineering submittal 10% x station price share 5.61% | Design stage key 19.6% of the engineering-submittal milestone | Q18: Annex 3 Design and engineering package (railway) allocated by station hardware share | R18: 55 | S18: =R18/1000 | T18: 46412 | U18: 46429 | V18: 14
A19: SH-DES | B19: Design and engineering package (per railway, allocated to the station) | C19: NRY-E1060 | D19: Preliminary design: SAR review and approval - Riyadh (Thumamah) | E19: ENG.NRY.PRE.APR | F19: Engineering | G19: NRY | H19: MS3 | I19: 0.1 | J19: =Station_BOQ!R5 | K19: =I19*62000000*J19 | L19: 0.2 | M19: =ROUND(K19*L19,0) | N19: 69616 | O19: =N19-M19 | P19: MS3 SAR approval of engineering 10% x station price share 5.61% | Design stage key 20.0% of the SAR-approval milestone | Q19: Annex 3 Design and engineering package (railway) allocated by station hardware share | R19: 59 | S19: =R19/1000 | T19: 46432 | U19: 46460 | V19: 15
A20: SH-DES | B20: Design and engineering package (per railway, allocated to the station) | C20: NRY-E1070 | D20: Detailed design: submittal (drawings, BOQ, data sheets) - Riyadh (Thumamah) | E20: ENG.NRY.DET.SUB | F20: Engineering | G20: NRY | H20: MS2 | I20: 0.1 | J20: =Station_BOQ!R5 | K20: =I20*62000000*J20 | L20: 0.392 | M20: =ROUND(K20*L20,0) | N20: 136447 | O20: =N20-M20 | P20: MS2 Engineering submittal 10% x station price share 5.61% | Design stage key 39.2% of the engineering-submittal milestone | Q20: Annex 3 Design and engineering package (railway) allocated by station hardware share | R20: 113 | S20: =R20/1000 | T20: 46432 | U20: 46469 | V20: 22
A21: SH-DES | B21: Design and engineering package (per railway, allocated to the station) | C21: NRY-E1080 | D21: Detailed design: SAR review and approval - Riyadh (Thumamah) | E21: ENG.NRY.DET.APR | F21: Engineering | G21: NRY | H21: MS3 | I21: 0.1 | J21: =Station_BOQ!R5 | K21: =I21*62000000*J21 | L21: 0.4 | M21: =ROUND(K21*L21,0) | N21: 139231 | O21: =N21-M21 | P21: MS3 SAR approval of engineering 10% x station price share 5.61% | Design stage key 40.0% of the SAR-approval milestone | Q21: Annex 3 Design and engineering package (railway) allocated by station hardware share | R21: 77 | S21: =R21/1000 | T21: 46470 | U21: 46490 | V21: 15
A22: SH-DES | B22: Design and engineering package (per railway, allocated to the station) | C22: NRY-E1090 | D22: IFC and shop drawings: submittal - Riyadh (Thumamah) | E22: ENG.NRY.IFC.SUB | F22: Engineering | G22: NRY | H22: MS2 | I22: 0.1 | J22: =Station_BOQ!R5 | K22: =I22*62000000*J22 | L22: 0.196 | M22: =ROUND(K22*L22,0) | N22: 68223 | O22: =N22-M22 | P22: MS2 Engineering submittal 10% x station price share 5.61% | Design stage key 19.6% of the engineering-submittal milestone | Q22: Annex 3 Design and engineering package (railway) allocated by station hardware share | R22: 51 | S22: =R22/1000 | T22: 46470 | U22: 46485 | V22: 12
A23: SH-DES | B23: Design and engineering package (per railway, allocated to the station) | C23: NRY-E1100 | D23: IFC and shop drawings: SAR approval and release - Riyadh (Thumamah) | E23: ENG.NRY.IFC.APR | F23: Engineering | G23: NRY | H23: MS3 | I23: 0.1 | J23: =Station_BOQ!R5 | K23: =I23*62000000*J23 | L23: 0.2 | M23: =ROUND(K23*L23,0) | N23: 69616 | O23: =N23-M23 | P23: MS3 SAR approval of engineering 10% x station price share 5.61% | Design stage key 20.0% of the SAR-approval milestone | Q23: Annex 3 Design and engineering package (railway) allocated by station hardware share | R23: 63 | S23: =R23/1000 | T23: 46488 | U23: 46506 | V23: 15
A24: SH-DES | B24: Design and engineering package (per railway, allocated to the station) | C24: NRY-E1110 | D24: HCIS Stage 3 and 4 documents: preparation - Riyadh (Thumamah) | E24: ENG.NRY.HCS.SUB | F24: Engineering | G24: NRY | H24: MS2 | I24: 0.1 | J24: =Station_BOQ!R5 | K24: =I24*62000000*J24 | L24: 0.049 | M24: =ROUND(K24*L24,0) | N24: 17056 | O24: =N24-M24 | P24: MS2 Engineering submittal 10% x station price share 5.61% | Design stage key 4.9% of the engineering-submittal milestone | Q24: Annex 3 Design and engineering package (railway) allocated by station hardware share | R24: 24 | S24: =R24/1000 | T24: 46443 | U24: 46485 | V24: 26
A25: SH-DES | B25: Design and engineering package (per railway, allocated to the station) | C25: NRY-E1120 | D25: HCIS Stage 3 and 4 documents: SAR final review and HCIS submission - Riyadh (Thumamah) | E25: ENG.NRY.HCS.APR | F25: Engineering | G25: NRY | H25: MS3 | I25: 0.1 | J25: =Station_BOQ!R5 | K25: =I25*62000000*J25 | L25: 0.05 | M25: =ROUND(K25*L25,0) | N25: 17404 | O25: =N25-M25 | P25: MS3 SAR approval of engineering 10% x station price share 5.61% | Design stage key 5.0% of the SAR-approval milestone | Q25: Annex 3 Design and engineering package (railway) allocated by station hardware share | R25: 14 | S25: =R25/1000 | T25: 46488 | U25: 46506 | V25: 15
A26: SH-DES, SH-TRN | B26: Design and engineering package (per railway, allocated to the station) and Training (per railway, allocated): documentation and training share | C26: NRY-E1130 | D26: As-built and O&M documentation: submittal - Riyadh (Thumamah) | E26: ENG.NRY.ASB.SUB | F26: Engineering | G26: NRY | H26: MS7 | I26: 0.1 | J26: =Station_BOQ!R5 | K26: =I26*62000000*J26 | L26: 0.15 | M26: =ROUND(K26*L26,0) | N26: 52212 | O26: =N26-M26 | P26: MS7 Final acceptance and handover 10% x station price share 5.61% | Fixed key 15% of final-acceptance milestone | Q26: Annex 3 documentation and training share | R26: 41 | S26: =R26/1000 | T26: 46695 | U26: 46734 | V26: 28
A27: SH-DES | B27: Design and engineering package (per railway, allocated to the station): documentation share | C27: NRY-E1140 | D27: As-built and O&M documentation: SAR review and approval - Riyadh (Thumamah) | E27: ENG.NRY.ASB.APR | F27: Engineering | G27: NRY | H27: MS7 | I27: 0.1 | J27: =Station_BOQ!R5 | K27: =I27*62000000*J27 | L27: 0.05 | M27: =ROUND(K27*L27,0) | N27: 17404 | O27: =N27-M27 | P27: MS7 Final acceptance and handover 10% x station price share 5.61% | Fixed key 5% | Q27: Annex 3 documentation share | R27: 22 | S27: =R27/1000 | T27: 46735 | U27: 46755 | V27: 15
A28: - | B28: No BOQ cost: administrative or review step with no payment milestone | C28: NRY-X1010 | D28: Enabling works: site preparation, setting out, temporary works and utilities clearance - Riyadh (Thumamah) | E28: CON.NRY.ENA | F28: Construction | G28: NRY | H28: MS5 | I28: 0.2 | J28: =Station_BOQ!R5 | K28: =I28*62000000*J28 | L28: 0.012112175 | M28: =ROUND(K28*L28,0) | N28: 8432 | O28: =N28-M28 | P28: MS5 Installation 20% x station price share 5.61% | BOQ civil share 30.3% x 4% (enabling: site preparation) | Q28: Annex 3 A6 Civil works (SAR 745,743) | R28: 54 | S28: =R28/1000 | T28: 46509 | U28: 46520 | V28: 10
A29: - | B29: No BOQ cost: administrative or review step with no payment milestone | C29: NRY-X1020 | D29: Enabling works: cable routes, duct-bank and cabinet plinth preparation - Riyadh (Thumamah) | E29: CON.NRY.ENA | F29: Construction | G29: NRY | H29: MS5 | I29: 0.2 | J29: =Station_BOQ!R5 | K29: =I29*62000000*J29 | L29: 0.018168263 | M29: =ROUND(K29*L29,0) | N29: 12648 | O29: =N29-M29 | P29: MS5 Installation 20% x station price share 5.61% | BOQ civil share 30.3% x 6% (enabling: routes, ducts, plinths) | Q29: Annex 3 A6 Civil works (SAR 745,743) | R29: 81 | S29: =R29/1000 | T29: 46530 | U29: 46548 | V29: 15
A30: A1 | B30: A1 CCTV system | C30: NRY-P1010 | D30: Manufacture CCTV cameras and analytics - Riyadh (Thumamah) | E30: PRO.NRY.CCT | F30: Procurement | G30: NRY | H30: MS4 | I30: 0.2 | J30: =Station_BOQ!R5 | K30: =I30*62000000*J30 | L30: 0.14806936 | M30: =ROUND(K30*L30,0) | N30: 103080 | O30: =N30-M30 | P30: MS4 Material delivery 20% x station price share 5.61% | BOQ section share 19.7% of station equipment x 75% (manufacture) | Q30: Annex 3 A1 CCTV system (SAR 338,989) | R30: 255 | S30: =R30/1000 | T30: 46509 | U30: 46580 | V30: 47
A31: A2 | B31: A2 Video management and video wall | C31: NRY-P1020 | D31: Manufacture video management servers, storage and video wall - Riyadh (Thumamah) | E31: PRO.NRY.VMS | F31: Procurement | G31: NRY | H31: MS4 | I31: 0.2 | J31: =Station_BOQ!R5 | K31: =I31*62000000*J31 | L31: 0.18220591 | M31: =ROUND(K31*L31,0) | N31: 126844 | O31: =N31-M31 | P31: MS4 Material delivery 20% x station price share 5.61% | BOQ section share 24.3% of station equipment x 75% (manufacture) | Q31: Annex 3 A2 Video management and wall (SAR 417,141) | R31: 314 | S31: =R31/1000 | T31: 46509 | U31: 46580 | V31: 47
A32: A3 | B32: A3 Access control and intercom | C32: NRY-P1030 | D32: Manufacture access control and intercom equipment - Riyadh (Thumamah) | E32: PRO.NRY.ACC | F32: Procurement | G32: NRY | H32: MS4 | I32: 0.2 | J32: =Station_BOQ!R5 | K32: =I32*62000000*J32 | L32: 0.019256193 | M32: =ROUND(K32*L32,0) | N32: 13405 | O32: =N32-M32 | P32: MS4 Material delivery 20% x station price share 5.61% | BOQ section share 2.6% of station equipment x 75% (manufacture) | Q32: Annex 3 A3 Access control and intercom (SAR 44,085) | R32: 33 | S32: =R32/1000 | T32: 46509 | U32: 46580 | V32: 47
A33: A4, A5 | B33: A4 UPS and A5 Poles, cabinets and network | C33: NRY-P1040 | D33: Manufacture UPS, network switches and field cabinets - Riyadh (Thumamah) | E33: PRO.NRY.UPN | F33: Procurement | G33: NRY | H33: MS4 | I33: 0.2 | J33: =Station_BOQ!R5 | K33: =I33*62000000*J33 | L33: 0.40046854 | M33: =ROUND(K33*L33,0) | N33: 278789 | O33: =N33-M33 | P33: MS4 Material delivery 20% x station price share 5.61% | BOQ section share 53.4% of station equipment x 75% (manufacture) | Q33: Annex 3 A4 UPS + A5 poles, cabinets and network (SAR 916,830) | R33: 691 | S33: =R33/1000 | T33: 46509 | U33: 46580 | V33: 47
A34: SH-FAT | B34: Factory acceptance test (per railway, allocated) | C34: NRY-P1050 | D34: Factory acceptance test at vendor premises - Riyadh (Thumamah) | E34: PRO.NRY.LOG | F34: Procurement | G34: NRY | H34: MS4 | I34: 0.2 | J34: =Station_BOQ!R5 | K34: =I34*62000000*J34 | L34: 0.05 | M34: =ROUND(K34*L34,0) | N34: 34808 | O34: =N34-M34 | P34: MS4 Material delivery 20% x station price share 5.61% | Fixed key 5% (FAT) | Q34: Annex 3 Factory acceptance test (railway), allocated by hardware share | R34: 216 | S34: =R34/1000 | T34: 46581 | U34: 46594 | V34: 10
A35: A1-A5 | B35: A1 to A5 equipment sections: logistics (shipping, customs, delivery) share | C35: NRY-P1060 | D35: Shipping and customs clearance - Riyadh (Thumamah) | E35: PRO.NRY.LOG | F35: Procurement | G35: NRY | H35: MS4 | I35: 0.2 | J35: =Station_BOQ!R5 | K35: =I35*62000000*J35 | L35: 0.15 | M35: =ROUND(K35*L35,0) | N35: 104424 | O35: =N35-M35 | P35: MS4 Material delivery 20% x station price share 5.61% | Fixed key 15% (shipping and customs) | Q35: Annex 3 equipment sections A1-A5 (logistics share) | R35: 431 | S35: =R35/1000 | T35: 46595 | U35: 46624 | V35: 22
A36: SH-SPR | B36: Commissioning spares (per railway, allocated) | C36: NRY-P1070 | D36: Delivery to station and receiving inspection - Riyadh (Thumamah) | E36: PRO.NRY.LOG | F36: Procurement | G36: NRY | H36: MS4 | I36: 0.2 | J36: =Station_BOQ!R5 | K36: =I36*62000000*J36 | L36: 0.05 | M36: =ROUND(K36*L36,0) | N36: 34808 | O36: =N36-M36 | P36: MS4 Material delivery 20% x station price share 5.61% | Fixed key 5% (delivery, receiving) incl. commissioning spares | Q36: Annex 3 Commissioning spares (railway), allocated by hardware share | R36: 216 | S36: =R36/1000 | T36: 46625 | U36: 46631 | V36: 5
A37: A6 | B37: A6 Civil works | C37: NRY-C1010 | D37: Civil: platform trenches and duct banks - Riyadh (Thumamah) | E37: CON.NRY.CIV | F37: Construction | G37: NRY | H37: MS5 | I37: 0.2 | J37: =Station_BOQ!R5 | K37: =I37*62000000*J37 | L37: 0.15140219 | M37: =ROUND(K37*L37,0) | N37: 105400 | O37: =N37-M37 | P37: MS5 Installation 20% x station price share 5.61% | BOQ civil share 30.3% x 50% (trenches and duct banks) | Q37: Annex 3 A6 Civil works (SAR 745,743) | R37: 350 | S37: =R37/1000 | T37: 46551 | U37: 46629 | V37: 57
A38: A6 | B38: A6 Civil works | C38: NRY-C1020 | D38: Civil: camera and ALPR pole foundations and poles - Riyadh (Thumamah) | E38: CON.NRY.CIV | F38: Construction | G38: NRY | H38: MS5 | I38: 0.2 | J38: =Station_BOQ!R5 | K38: =I38*62000000*J38 | L38: 0.12112175 | M38: =ROUND(K38*L38,0) | N38: 84320 | O38: =N38-M38 | P38: MS5 Installation 20% x station price share 5.61% | BOQ civil share 30.3% x 40% (poles) | Q38: Annex 3 A6 Civil works (SAR 745,743) | R38: 269 | S38: =R38/1000 | T38: 46602 | U38: 46665 | V38: 45
A39: A1-A5 | B39: A1 to A5 equipment sections: installation share (works included in unit prices) | C39: NRY-C2010 | D39: Install UPS, network switches and field cabinets - Riyadh (Thumamah) | E39: CON.NRY.INS | F39: Construction | G39: NRY | H39: MS5 | I39: 0.2 | J39: =Station_BOQ!R5 | K39: =I39*62000000*J39 | L39: 0.13943912 | M39: =ROUND(K39*L39,0) | N39: 97072 | O39: =N39-M39 | P39: MS5 Installation 20% x station price share 5.61% | Installation key 20% x (1 - civil share 30.3%) | Q39: Annex 3 equipment sections A1-A5 (installation share) | R39: 162 | S39: =R39/1000 | T39: 46632 | U39: 46650 | V39: 13
A40: A1-A5 | B40: A1 to A5 equipment sections: installation share (works included in unit prices) | C40: NRY-C2020 | D40: Cabling and termination (power, fibre, data) - Riyadh (Thumamah) | E40: CON.NRY.INS | F40: Construction | G40: NRY | H40: MS5 | I40: 0.2 | J40: =Station_BOQ!R5 | K40: =I40*62000000*J40 | L40: 0.20915869 | M40: =ROUND(K40*L40,0) | N40: 145607 | O40: =N40-M40 | P40: MS5 Installation 20% x station price share 5.61% | Installation key 30% x (1 - civil share 30.3%) | Q40: Annex 3 equipment sections A1-A5 (installation share) | R40: 323 | S40: =R40/1000 | T40: 46638 | U40: 46670 | V40: 22
A41: A1-A5 | B41: A1 to A5 equipment sections: installation share (works included in unit prices) | C41: NRY-C2030 | D41: Install and aim CCTV cameras - Riyadh (Thumamah) | E41: CON.NRY.INS | F41: Construction | G41: NRY | H41: MS5 | I41: 0.2 | J41: =Station_BOQ!R5 | K41: =I41*62000000*J41 | L41: 0.1742989 | M41: =ROUND(K41*L41,0) | N41: 121339 | O41: =N41-M41 | P41: MS5 Installation 20% x station price share 5.61% | Installation key 25% x (1 - civil share 30.3%) | Q41: Annex 3 equipment sections A1-A5 (installation share) | R41: 269 | S41: =R41/1000 | T41: 46671 | U41: 46694 | V41: 18
A42: A1-A5 | B42: A1 to A5 equipment sections: installation share (works included in unit prices) | C42: NRY-C2040 | D42: Install video management, video wall and control-room equipment - Riyadh (Thumamah) | E42: CON.NRY.INS | F42: Construction | G42: NRY | H42: MS5 | I42: 0.2 | J42: =Station_BOQ!R5 | K42: =I42*62000000*J42 | L42: 0.10457934 | M42: =ROUND(K42*L42,0) | N42: 72804 | O42: =N42-M42 | P42: MS5 Installation 20% x station price share 5.61% | Installation key 15% x (1 - civil share 30.3%) | Q42: Annex 3 equipment sections A1-A5 (installation share) | R42: 162 | S42: =R42/1000 | T42: 46651 | U42: 46672 | V42: 15
A43: A1-A5 | B43: A1 to A5 equipment sections: installation share (works included in unit prices) | C43: NRY-C2050 | D43: Install access control and intercom - Riyadh (Thumamah) | E43: CON.NRY.INS | F43: Construction | G43: NRY | H43: MS5 | I43: 0.2 | J43: =Station_BOQ!R5 | K43: =I43*62000000*J43 | L43: 0.069719562 | M43: =ROUND(K43*L43,0) | N43: 48536 | O43: =N43-M43 | P43: MS5 Installation 20% x station price share 5.61% | Installation key 10% x (1 - civil share 30.3%) | Q43: Annex 3 equipment sections A1-A5 (installation share) | R43: 108 | S43: =R43/1000 | T43: 46658 | U43: 46674 | V43: 13
A44: A1-A5 | B44: A1 to A5 equipment sections: testing and commissioning share | C44: NRY-T1010 | D44: Pre-commissioning and loop checks - Riyadh (Thumamah) | E44: COM.NRY.TST | F44: Commissioning and handover | G44: NRY | H44: MS6 | I44: 0.1 | J44: =Station_BOQ!R5 | K44: =I44*62000000*J44 | L44: 0.388 | M44: =ROUND(K44*L44,0) | N44: 135054 | O44: =N44-M44 | P44: MS6 Testing and commissioning (SAT) 10% x station price share 5.61% | Fixed key 40% of SAT milestone | Q44: Annex 3 equipment sections A1-A5 (testing share) | R44: 162 | S44: =R44/1000 | T44: 46695 | U44: 46701 | V44: 5
A45: A1-A5 | B45: A1 to A5 equipment sections: testing and commissioning share | C45: NRY-T1020 | D45: Site acceptance test (SAT) and commissioning - Riyadh (Thumamah) | E45: COM.NRY.TST | F45: Commissioning and handover | G45: NRY | H45: MS6 | I45: 0.1 | J45: =Station_BOQ!R5 | K45: =I45*62000000*J45 | L45: 0.582 | M45: =ROUND(K45*L45,0) | N45: 202582 | O45: =N45-M45 | P45: MS6 Testing and commissioning (SAT) 10% x station price share 5.61% | Fixed key 60% of SAT milestone | Q45: Annex 3 equipment sections A1-A5 (testing share) | R45: 189 | S45: =R45/1000 | T45: 46702 | U45: 46713 | V45: 8
A46: SH-TRN | B46: Training (per railway, allocated) | C46: NRY-T2010 | D46: Operator and maintenance training - Riyadh (Thumamah) | E46: COM.NRY.TRN | F46: Commissioning and handover | G46: NRY | H46: MS7 | I46: 0.1 | J46: =Station_BOQ!R5 | K46: =I46*62000000*J46 | L46: 0.15 | M46: =ROUND(K46*L46,0) | N46: 52212 | O46: =N46-M46 | P46: MS7 Final acceptance and handover 10% x station price share 5.61% | Fixed key 15% | Q46: Annex 3 Training (railway), allocated by hardware share | R46: 108 | S46: =R46/1000 | T46: 46714 | U46: 46727 | V46: 10
A47: A1-A5 | B47: A1 to A5 equipment sections: trial operation share | C47: NRY-T2020 | D47: Trial operation (maximum 45 days) - Riyadh (Thumamah) | E47: COM.NRY.TOA | F47: Commissioning and handover | G47: NRY | H47: MS7 | I47: 0.1 | J47: =Station_BOQ!R5 | K47: =I47*62000000*J47 | L47: 0.35 | M47: =ROUND(K47*L47,0) | N47: 121828 | O47: =N47-M47 | P47: MS7 Final acceptance and handover 10% x station price share 5.61% | Fixed key 35% | Q47: Annex 3 equipment sections A1-A5 (trial operation share) | R47: 162 | S47: =R47/1000 | T47: 46714 | U47: 46755 | V47: 30
A48: A1-A5 | B48: A1 to A5 equipment sections: handover share | C48: NRY-T3010 | D48: Taking-over application, SAR review and handover - Riyadh (Thumamah) | E48: COM.NRY.TOA | F48: Commissioning and handover | G48: NRY | H48: MS7 | I48: 0.1 | J48: =Station_BOQ!R5 | K48: =I48*62000000*J48 | L48: 0.3 | M48: =ROUND(K48*L48,0) | N48: 104424 | O48: =N48-M48 | P48: MS7 Final acceptance and handover 10% x station price share 5.61% | Fixed key 30% | Q48: Annex 3 equipment sections A1-A5 (handover share) | R48: 162 | S48: =R48/1000 | T48: 46756 | U48: 46785 | V48: 22
A49: A1-A5 | B49: A1 to A5 equipment sections: mock-up approval share (carved from the testing share) | C49: NRY-T1030 | D49: Mock-up approval: site visit and SAR approval of the executed works (roll-out to other stations) - Riyadh (Thumamah) | E49: COM.NRY.MOK | F49: Commissioning and handover | G49: NRY | H49: MS6 | I49: 0.1 | J49: =Station_BOQ!R5 | K49: =I49*62000000*J49 | L49: 0.03 | M49: =ROUND(K49*L49,0) | N49: 10442 | O49: =N49-M49 | P49: MS6 Testing and commissioning (SAT) 10% x station price share 5.61% | Mock-up approval key 3% of the SAT milestone (no separate Annex 3 item; carved from the testing share) | Q49: Annex 3 equipment sections A1-A5 (testing share) | R49: 27 | S49: =R49/1000 | T49: 46695 | U49: 46726 | V49: 22
A50: SH-DES | B50: Design and engineering package (per railway, allocated to the station) | C50: HMK-E1010 | D50: Survey: submittal of site survey and as-found report - Makkah | E50: ENG.HMK.SRV.SUB | F50: Engineering | G50: HMK | H50: MS2 | I50: 0.1 | J50: =Station_BOQ!R6 | K50: =I50*62000000*J50 | L50: 0.069 | M50: =ROUND(K50*L50,0) | N50: 67000 | O50: =N50-M50 | P50: MS2 Engineering submittal 10% x station price share 15.66% | Design stage key 6.9% of the engineering-submittal milestone | Q50: Annex 3 Design and engineering package (railway) allocated by station hardware share | R50: 124 | S50: =R50/1000 | T50: 46390 | U50: 46422 | V50: 25
A51: SH-DES | B51: Design and engineering package (per railway, allocated to the station) | C51: HMK-E1020 | D51: Survey: SAR approval of survey report - Makkah | E51: ENG.HMK.SRV.APR | F51: Engineering | G51: HMK | H51: MS3 | I51: 0.1 | J51: =Station_BOQ!R6 | K51: =I51*62000000*J51 | L51: 0.05 | M51: =ROUND(K51*L51,0) | N51: 48550 | O51: =N51-M51 | P51: MS3 SAR approval of engineering 10% x station price share 15.66% | Design stage key 5.0% of the SAR-approval milestone | Q51: Annex 3 Design and engineering package (railway) allocated by station hardware share | R51: 53 | S51: =R51/1000 | T51: 46425 | U51: 46446 | V51: 15
A52: SH-DES | B52: Design and engineering package (per railway, allocated to the station) | C52: HMK-E1030 | D52: Concept design: submittal - Makkah | E52: ENG.HMK.CNC.SUB | F52: Engineering | G52: HMK | H52: MS2 | I52: 0.1 | J52: =Station_BOQ!R6 | K52: =I52*62000000*J52 | L52: 0.098 | M52: =ROUND(K52*L52,0) | N52: 95159 | O52: =N52-M52 | P52: MS2 Engineering submittal 10% x station price share 15.66% | Design stage key 9.8% of the engineering-submittal milestone | Q52: Annex 3 Design and engineering package (railway) allocated by station hardware share | R52: 51 | S52: =R52/1000 | T52: 46425 | U52: 46432 | V52: 6
A53: SH-DES | B53: Design and engineering package (per railway, allocated to the station) | C53: HMK-E1040 | D53: Concept design: SAR review and approval - Makkah | E53: ENG.HMK.CNC.APR | F53: Engineering | G53: HMK | H53: MS3 | I53: 0.1 | J53: =Station_BOQ!R6 | K53: =I53*62000000*J53 | L53: 0.1 | M53: =ROUND(K53*L53,0) | N53: 97101 | O53: =N53-M53 | P53: MS3 SAR approval of engineering 10% x station price share 15.66% | Design stage key 10.0% of the SAR-approval milestone | Q53: Annex 3 Design and engineering package (railway) allocated by station hardware share | R53: 126 | S53: =R53/1000 | T53: 46433 | U53: 46461 | V53: 15
A54: SH-DES | B54: Design and engineering package (per railway, allocated to the station) | C54: HMK-E1050 | D54: Preliminary design: submittal - Makkah | E54: ENG.HMK.PRE.SUB | F54: Engineering | G54: HMK | H54: MS2 | I54: 0.1 | J54: =Station_BOQ!R6 | K54: =I54*62000000*J54 | L54: 0.196 | M54: =ROUND(K54*L54,0) | N54: 190318 | O54: =N54-M54 | P54: MS2 Engineering submittal 10% x station price share 15.66% | Design stage key 19.6% of the engineering-submittal milestone | Q54: Annex 3 Design and engineering package (railway) allocated by station hardware share | R54: 127 | S54: =R54/1000 | T54: 46433 | U54: 46447 | V54: 10
A55: SH-DES | B55: Design and engineering package (per railway, allocated to the station) | C55: HMK-E1060 | D55: Preliminary design: SAR review and approval - Makkah | E55: ENG.HMK.PRE.APR | F55: Engineering | G55: HMK | H55: MS3 | I55: 0.1 | J55: =Station_BOQ!R6 | K55: =I55*62000000*J55 | L55: 0.2 | M55: =ROUND(K55*L55,0) | N55: 194202 | O55: =N55-M55 | P55: MS3 SAR approval of engineering 10% x station price share 15.66% | Design stage key 20.0% of the SAR-approval milestone | Q55: Annex 3 Design and engineering package (railway) allocated by station hardware share | R55: 191 | S55: =R55/1000 | T55: 46448 | U55: 46475 | V55: 15
A56: SH-DES | B56: Design and engineering package (per railway, allocated to the station) | C56: HMK-E1070 | D56: Detailed design: submittal (drawings, BOQ, data sheets) - Makkah | E56: ENG.HMK.DET.SUB | F56: Engineering | G56: HMK | H56: MS2 | I56: 0.1 | J56: =Station_BOQ!R6 | K56: =I56*62000000*J56 | L56: 0.392 | M56: =ROUND(K56*L56,0) | N56: 380636 | O56: =N56-M56 | P56: MS2 Engineering submittal 10% x station price share 15.66% | Design stage key 39.2% of the engineering-submittal milestone | Q56: Annex 3 Design and engineering package (railway) allocated by station hardware share | R56: 274 | S56: =R56/1000 | T56: 46448 | U56: 46476 | V56: 16
A57: SH-DES | B57: Design and engineering package (per railway, allocated to the station) | C57: HMK-E1080 | D57: Detailed design: SAR review and approval - Makkah | E57: ENG.HMK.DET.APR | F57: Engineering | G57: HMK | H57: MS3 | I57: 0.1 | J57: =Station_BOQ!R6 | K57: =I57*62000000*J57 | L57: 0.4 | M57: =ROUND(K57*L57,0) | N57: 388404 | O57: =N57-M57 | P57: MS3 SAR approval of engineering 10% x station price share 15.66% | Design stage key 40.0% of the SAR-approval milestone | Q57: Annex 3 Design and engineering package (railway) allocated by station hardware share | R57: 257 | S57: =R57/1000 | T57: 46477 | U57: 46497 | V57: 15
A58: SH-DES | B58: Design and engineering package (per railway, allocated to the station) | C58: HMK-E1090 | D58: IFC and shop drawings: submittal - Makkah | E58: ENG.HMK.IFC.SUB | F58: Engineering | G58: HMK | H58: MS2 | I58: 0.1 | J58: =Station_BOQ!R6 | K58: =I58*62000000*J58 | L58: 0.196 | M58: =ROUND(K58*L58,0) | N58: 190318 | O58: =N58-M58 | P58: MS2 Engineering submittal 10% x station price share 15.66% | Design stage key 19.6% of the engineering-submittal milestone | Q58: Annex 3 Design and engineering package (railway) allocated by station hardware share | R58: 101 | S58: =R58/1000 | T58: 46477 | U58: 46485 | V58: 7
A59: SH-DES | B59: Design and engineering package (per railway, allocated to the station) | C59: HMK-E1100 | D59: IFC and shop drawings: SAR approval and release - Makkah | E59: ENG.HMK.IFC.APR | F59: Engineering | G59: HMK | H59: MS3 | I59: 0.1 | J59: =Station_BOQ!R6 | K59: =I59*62000000*J59 | L59: 0.2 | M59: =ROUND(K59*L59,0) | N59: 194202 | O59: =N59-M59 | P59: MS3 SAR approval of engineering 10% x station price share 15.66% | Design stage key 20.0% of the SAR-approval milestone | Q59: Annex 3 Design and engineering package (railway) allocated by station hardware share | R59: 217 | S59: =R59/1000 | T59: 46488 | U59: 46506 | V59: 15
A60: SH-DES | B60: Design and engineering package (per railway, allocated to the station) | C60: HMK-E1110 | D60: HCIS Stage 3 and 4 documents: preparation - Makkah | E60: ENG.HMK.HCS.SUB | F60: Engineering | G60: HMK | H60: MS2 | I60: 0.1 | J60: =Station_BOQ!R6 | K60: =I60*62000000*J60 | L60: 0.049 | M60: =ROUND(K60*L60,0) | N60: 47579 | O60: =N60-M60 | P60: MS2 Engineering submittal 10% x station price share 15.66% | Design stage key 4.9% of the engineering-submittal milestone | Q60: Annex 3 Design and engineering package (railway) allocated by station hardware share | R60: 56 | S60: =R60/1000 | T60: 46463 | U60: 46485 | V60: 17
A61: SH-DES | B61: Design and engineering package (per railway, allocated to the station) | C61: HMK-E1120 | D61: HCIS Stage 3 and 4 documents: SAR final review and HCIS submission - Makkah | E61: ENG.HMK.HCS.APR | F61: Engineering | G61: HMK | H61: MS3 | I61: 0.1 | J61: =Station_BOQ!R6 | K61: =I61*62000000*J61 | L61: 0.05 | M61: =ROUND(K61*L61,0) | N61: 48550 | O61: =N61-M61 | P61: MS3 SAR approval of engineering 10% x station price share 15.66% | Design stage key 5.0% of the SAR-approval milestone | Q61: Annex 3 Design and engineering package (railway) allocated by station hardware share | R61: 50 | S61: =R61/1000 | T61: 46488 | U61: 46506 | V61: 15
A62: SH-DES, SH-TRN | B62: Design and engineering package (per railway, allocated to the station) and Training (per railway, allocated): documentation and training share | C62: HMK-E1130 | D62: As-built and O&M documentation: submittal - Makkah | E62: ENG.HMK.ASB.SUB | F62: Engineering | G62: HMK | H62: MS7 | I62: 0.1 | J62: =Station_BOQ!R6 | K62: =I62*62000000*J62 | L62: 0.15 | M62: =ROUND(K62*L62,0) | N62: 145651 | O62: =N62-M62 | P62: MS7 Final acceptance and handover 10% x station price share 15.66% | Fixed key 15% of final-acceptance milestone | Q62: Annex 3 documentation and training share | R62: 133 | S62: =R62/1000 | T62: 46820 | U62: 46889 | V62: 45
A63: SH-DES | B63: Design and engineering package (per railway, allocated to the station): documentation share | C63: HMK-E1140 | D63: As-built and O&M documentation: SAR review and approval - Makkah | E63: ENG.HMK.ASB.APR | F63: Engineering | G63: HMK | H63: MS7 | I63: 0.1 | J63: =Station_BOQ!R6 | K63: =I63*62000000*J63 | L63: 0.05 | M63: =ROUND(K63*L63,0) | N63: 48550 | O63: =N63-M63 | P63: MS7 Final acceptance and handover 10% x station price share 15.66% | Fixed key 5% | Q63: Annex 3 documentation share | R63: 44 | S63: =R63/1000 | T63: 46890 | U63: 46910 | V63: 15
A64: - | B64: No BOQ cost: administrative or review step with no payment milestone | C64: HMK-X1010 | D64: Enabling works: site preparation, setting out, temporary works and utilities clearance - Makkah | E64: CON.HMK.ENA | F64: Construction | G64: HMK | H64: MS5 | I64: 0.2 | J64: =Station_BOQ!R6 | K64: =I64*62000000*J64 | L64: 0.0040508196 | M64: =ROUND(K64*L64,0) | N64: 7867 | O64: =N64-M64 | P64: MS5 Installation 20% x station price share 15.66% | BOQ civil share 10.1% x 4% (enabling: site preparation) | Q64: Annex 3 A6 Civil works (SAR 571,639) | R64: 150 | S64: =R64/1000 | T64: 46509 | U64: 46520 | V64: 10
A65: - | B65: No BOQ cost: administrative or review step with no payment milestone | C65: HMK-X1020 | D65: Enabling works: cable routes, duct-bank and cabinet plinth preparation - Makkah | E65: CON.HMK.ENA | F65: Construction | G65: HMK | H65: MS5 | I65: 0.2 | J65: =Station_BOQ!R6 | K65: =I65*62000000*J65 | L65: 0.0060762294 | M65: =ROUND(K65*L65,0) | N65: 11800 | O65: =N65-M65 | P65: MS5 Installation 20% x station price share 15.66% | BOQ civil share 10.1% x 6% (enabling: routes, ducts, plinths) | Q65: Annex 3 A6 Civil works (SAR 571,639) | R65: 226 | S65: =R65/1000 | T65: 46530 | U65: 46548 | V65: 15
A66: A1 | B66: A1 CCTV system | C66: HMK-P1010 | D66: Manufacture CCTV cameras and analytics - Makkah | E66: PRO.HMK.CCT | F66: Procurement | G66: HMK | H66: MS4 | I66: 0.2 | J66: =Station_BOQ!R6 | K66: =I66*62000000*J66 | L66: 0.24396264 | M66: =ROUND(K66*L66,0) | N66: 473780 | O66: =N66-M66 | P66: MS4 Material delivery 20% x station price share 15.66% | BOQ section share 32.5% of station equipment x 75% (manufacture) | Q66: Annex 3 A1 CCTV system (SAR 1,650,175) | R66: 1175 | S66: =R66/1000 | T66: 46509 | U66: 46628 | V66: 81
A67: A2 | B67: A2 Video management and video wall | C67: HMK-P1020 | D67: Manufacture video management servers, storage and video wall - Makkah | E67: PRO.HMK.VMS | F67: Procurement | G67: HMK | H67: MS4 | I67: 0.2 | J67: =Station_BOQ!R6 | K67: =I67*62000000*J67 | L67: 0.081642975 | M67: =ROUND(K67*L67,0) | N67: 158552 | O67: =N67-M67 | P67: MS4 Material delivery 20% x station price share 15.66% | BOQ section share 10.9% of station equipment x 75% (manufacture) | Q67: Annex 3 A2 Video management and wall (SAR 552,237) | R67: 393 | S67: =R67/1000 | T67: 46509 | U67: 46628 | V67: 81
A68: A3 | B68: A3 Access control and intercom | C68: HMK-P1030 | D68: Manufacture access control and intercom equipment - Makkah | E68: PRO.HMK.ACC | F68: Procurement | G68: HMK | H68: MS4 | I68: 0.2 | J68: =Station_BOQ!R6 | K68: =I68*62000000*J68 | L68: 0.0065175469 | M68: =ROUND(K68*L68,0) | N68: 12657 | O68: =N68-M68 | P68: MS4 Material delivery 20% x station price share 15.66% | BOQ section share 0.9% of station equipment x 75% (manufacture) | Q68: Annex 3 A3 Access control and intercom (SAR 44,085) | R68: 31 | S68: =R68/1000 | T68: 46509 | U68: 46628 | V68: 81
A69: A4, A5 | B69: A4 UPS and A5 Poles, cabinets and network | C69: HMK-P1040 | D69: Manufacture UPS, network switches and field cabinets - Makkah | E69: PRO.HMK.UPN | F69: Procurement | G69: HMK | H69: MS4 | I69: 0.2 | J69: =Station_BOQ!R6 | K69: =I69*62000000*J69 | L69: 0.41787684 | M69: =ROUND(K69*L69,0) | N69: 811524 | O69: =N69-M69 | P69: MS4 Material delivery 20% x station price share 15.66% | BOQ section share 55.7% of station equipment x 75% (manufacture) | Q69: Annex 3 A4 UPS + A5 poles, cabinets and network (SAR 2,826,539) | R69: 2011 | S69: =R69/1000 | T69: 46509 | U69: 46628 | V69: 81
A70: SH-FAT | B70: Factory acceptance test (per railway, allocated) | C70: HMK-P1050 | D70: Factory acceptance test at vendor premises - Makkah | E70: PRO.HMK.LOG | F70: Procurement | G70: HMK | H70: MS4 | I70: 0.2 | J70: =Station_BOQ!R6 | K70: =I70*62000000*J70 | L70: 0.05 | M70: =ROUND(K70*L70,0) | N70: 97101 | O70: =N70-M70 | P70: MS4 Material delivery 20% x station price share 15.66% | Fixed key 5% (FAT) | Q70: Annex 3 Factory acceptance test (railway), allocated by hardware share | R70: 601 | S70: =R70/1000 | T70: 46629 | U70: 46642 | V70: 10
A71: A1-A5 | B71: A1 to A5 equipment sections: logistics (shipping, customs, delivery) share | C71: HMK-P1060 | D71: Shipping and customs clearance - Makkah | E71: PRO.HMK.LOG | F71: Procurement | G71: HMK | H71: MS4 | I71: 0.2 | J71: =Station_BOQ!R6 | K71: =I71*62000000*J71 | L71: 0.15 | M71: =ROUND(K71*L71,0) | N71: 291303 | O71: =N71-M71 | P71: MS4 Material delivery 20% x station price share 15.66% | Fixed key 15% (shipping and customs) | Q71: Annex 3 equipment sections A1-A5 (logistics share) | R71: 1204 | S71: =R71/1000 | T71: 46643 | U71: 46692 | V71: 35
A72: SH-SPR | B72: Commissioning spares (per railway, allocated) | C72: HMK-P1070 | D72: Delivery to station and receiving inspection - Makkah | E72: PRO.HMK.LOG | F72: Procurement | G72: HMK | H72: MS4 | I72: 0.2 | J72: =Station_BOQ!R6 | K72: =I72*62000000*J72 | L72: 0.05 | M72: =ROUND(K72*L72,0) | N72: 97101 | O72: =N72-M72 | P72: MS4 Material delivery 20% x station price share 15.66% | Fixed key 5% (delivery, receiving) incl. commissioning spares | Q72: Annex 3 Commissioning spares (railway), allocated by hardware share | R72: 601 | S72: =R72/1000 | T72: 46693 | U72: 46699 | V72: 5
A73: A6 | B73: A6 Civil works | C73: HMK-C1010 | D73: Civil: platform trenches and duct banks - Makkah | E73: CON.HMK.CIV | F73: Construction | G73: HMK | H73: MS5 | I73: 0.2 | J73: =Station_BOQ!R6 | K73: =I73*62000000*J73 | L73: 0.050635245 | M73: =ROUND(K73*L73,0) | N73: 98335 | O73: =N73-M73 | P73: MS5 Installation 20% x station price share 15.66% | BOQ civil share 10.1% x 50% (trenches and duct banks) | Q73: Annex 3 A6 Civil works (SAR 571,639) | R73: 977 | S73: =R73/1000 | T73: 46551 | U73: 46616 | V73: 48
A74: A6 | B74: A6 Civil works | C74: HMK-C1020 | D74: Civil: camera and ALPR pole foundations and poles - Makkah | E74: CON.HMK.CIV | F74: Construction | G74: HMK | H74: MS5 | I74: 0.2 | J74: =Station_BOQ!R6 | K74: =I74*62000000*J74 | L74: 0.040508196 | M74: =ROUND(K74*L74,0) | N74: 78668 | O74: =N74-M74 | P74: MS5 Installation 20% x station price share 15.66% | BOQ civil share 10.1% x 40% (poles) | Q74: Annex 3 A6 Civil works (SAR 571,639) | R74: 752 | S74: =R74/1000 | T74: 46594 | U74: 46644 | V74: 37
A75: A1-A5 | B75: A1 to A5 equipment sections: installation share (works included in unit prices) | C75: HMK-C2010 | D75: Install UPS, network switches and field cabinets - Makkah | E75: CON.HMK.INS | F75: Construction | G75: HMK | H75: MS5 | I75: 0.2 | J75: =Station_BOQ!R6 | K75: =I75*62000000*J75 | L75: 0.1797459 | M75: =ROUND(K75*L75,0) | N75: 349070 | O75: =N75-M75 | P75: MS5 Installation 20% x station price share 15.66% | Installation key 20% x (1 - civil share 10.1%) | Q75: Annex 3 equipment sections A1-A5 (installation share) | R75: 451 | S75: =R75/1000 | T75: 46700 | U75: 46733 | V75: 24
A76: A1-A5 | B76: A1 to A5 equipment sections: installation share (works included in unit prices) | C76: HMK-C2020 | D76: Cabling and termination (power, fibre, data) - Makkah | E76: CON.HMK.INS | F76: Construction | G76: HMK | H76: MS5 | I76: 0.2 | J76: =Station_BOQ!R6 | K76: =I76*62000000*J76 | L76: 0.26961885 | M76: =ROUND(K76*L76,0) | N76: 523604 | O76: =N76-M76 | P76: MS5 Installation 20% x station price share 15.66% | Installation key 30% x (1 - civil share 10.1%) | Q76: Annex 3 equipment sections A1-A5 (installation share) | R76: 902 | S76: =R76/1000 | T76: 46712 | U76: 46768 | V76: 41
A77: A1-A5 | B77: A1 to A5 equipment sections: installation share (works included in unit prices) | C77: HMK-C2030 | D77: Install and aim CCTV cameras - Makkah | E77: CON.HMK.INS | F77: Construction | G77: HMK | H77: MS5 | I77: 0.2 | J77: =Station_BOQ!R6 | K77: =I77*62000000*J77 | L77: 0.22468238 | M77: =ROUND(K77*L77,0) | N77: 436337 | O77: =N77-M77 | P77: MS5 Installation 20% x station price share 15.66% | Installation key 25% x (1 - civil share 10.1%) | Q77: Annex 3 equipment sections A1-A5 (installation share) | R77: 752 | S77: =R77/1000 | T77: 46769 | U77: 46819 | V77: 32
A78: A1-A5 | B78: A1 to A5 equipment sections: installation share (works included in unit prices) | C78: HMK-C2040 | D78: Install video management, video wall and control-room equipment - Makkah | E78: CON.HMK.INS | F78: Construction | G78: HMK | H78: MS5 | I78: 0.2 | J78: =Station_BOQ!R6 | K78: =I78*62000000*J78 | L78: 0.13480943 | M78: =ROUND(K78*L78,0) | N78: 261802 | O78: =N78-M78 | P78: MS5 Installation 20% x station price share 15.66% | Installation key 15% x (1 - civil share 10.1%) | Q78: Annex 3 equipment sections A1-A5 (installation share) | R78: 451 | S78: =R78/1000 | T78: 46734 | U78: 46771 | V78: 28
A79: A1-A5 | B79: A1 to A5 equipment sections: installation share (works included in unit prices) | C79: HMK-C2050 | D79: Install access control and intercom - Makkah | E79: CON.HMK.INS | F79: Construction | G79: HMK | H79: MS5 | I79: 0.2 | J79: =Station_BOQ!R6 | K79: =I79*62000000*J79 | L79: 0.089872951 | M79: =ROUND(K79*L79,0) | N79: 174535 | O79: =N79-M79 | P79: MS5 Installation 20% x station price share 15.66% | Installation key 10% x (1 - civil share 10.1%) | Q79: Annex 3 equipment sections A1-A5 (installation share) | R79: 301 | S79: =R79/1000 | T79: 46744 | U79: 46777 | V79: 24
A80: A1-A5 | B80: A1 to A5 equipment sections: testing and commissioning share | C80: HMK-T1010 | D80: Pre-commissioning and loop checks - Makkah | E80: COM.HMK.TST | F80: Commissioning and handover | G80: HMK | H80: MS6 | I80: 0.1 | J80: =Station_BOQ!R6 | K80: =I80*62000000*J80 | L80: 0.4 | M80: =ROUND(K80*L80,0) | N80: 388404 | O80: =N80-M80 | P80: MS6 Testing and commissioning (SAT) 10% x station price share 15.66% | Fixed key 40% of SAT milestone | Q80: Annex 3 equipment sections A1-A5 (testing share) | R80: 451 | S80: =R80/1000 | T80: 46820 | U80: 46835 | V80: 12
A81: A1-A5 | B81: A1 to A5 equipment sections: testing and commissioning share | C81: HMK-T1020 | D81: Site acceptance test (SAT) and commissioning - Makkah | E81: COM.HMK.TST | F81: Commissioning and handover | G81: HMK | H81: MS6 | I81: 0.1 | J81: =Station_BOQ!R6 | K81: =I81*62000000*J81 | L81: 0.6 | M81: =ROUND(K81*L81,0) | N81: 582605 | O81: =N81-M81 | P81: MS6 Testing and commissioning (SAT) 10% x station price share 15.66% | Fixed key 60% of SAT milestone | Q81: Annex 3 equipment sections A1-A5 (testing share) | R81: 601 | S81: =R81/1000 | T81: 46838 | U81: 46861 | V81: 18
A82: SH-TRN | B82: Training (per railway, allocated) | C82: HMK-T2010 | D82: Operator and maintenance training - Makkah | E82: COM.HMK.TRN | F82: Commissioning and handover | G82: HMK | H82: MS7 | I82: 0.1 | J82: =Station_BOQ!R6 | K82: =I82*62000000*J82 | L82: 0.15 | M82: =ROUND(K82*L82,0) | N82: 145651 | O82: =N82-M82 | P82: MS7 Final acceptance and handover 10% x station price share 15.66% | Fixed key 15% | Q82: Annex 3 Training (railway), allocated by hardware share | R82: 301 | S82: =R82/1000 | T82: 46862 | U82: 46882 | V82: 10
A83: A1-A5 | B83: A1 to A5 equipment sections: trial operation share | C83: HMK-T2020 | D83: Trial operation (maximum 45 days) - Makkah | E83: COM.HMK.TOA | F83: Commissioning and handover | G83: HMK | H83: MS7 | I83: 0.1 | J83: =Station_BOQ!R6 | K83: =I83*62000000*J83 | L83: 0.35 | M83: =ROUND(K83*L83,0) | N83: 339853 | O83: =N83-M83 | P83: MS7 Final acceptance and handover 10% x station price share 15.66% | Fixed key 35% | Q83: Annex 3 equipment sections A1-A5 (trial operation share) | R83: 451 | S83: =R83/1000 | T83: 46862 | U83: 46910 | V83: 30
A84: A1-A5 | B84: A1 to A5 equipment sections: handover share | C84: HMK-T3010 | D84: Taking-over application, SAR review and handover - Makkah | E84: COM.HMK.TOA | F84: Commissioning and handover | G84: HMK | H84: MS7 | I84: 0.1 | J84: =Station_BOQ!R6 | K84: =I84*62000000*J84 | L84: 0.3 | M84: =ROUND(K84*L84,0) | N84: 291303 | O84: =N84-M84 | P84: MS7 Final acceptance and handover 10% x station price share 15.66% | Fixed key 30% | Q84: Annex 3 equipment sections A1-A5 (handover share) | R84: 451 | S84: =R84/1000 | T84: 46911 | U84: 46940 | V84: 22
A85: SH-DES | B85: Design and engineering package (per railway, allocated to the station) | C85: ERY-E1010 | D85: Survey: submittal of site survey and as-found report - Riyadh (Malaz) | E85: ENG.ERY.SRV.SUB | F85: Engineering | G85: ERY | H85: MS2 | I85: 0.1 | J85: =Station_BOQ!R7 | K85: =I85*62000000*J85 | L85: 0.069 | M85: =ROUND(K85*L85,0) | N85: 21331 | O85: =N85-M85 | P85: MS2 Engineering submittal 10% x station price share 4.99% | Design stage key 6.9% of the engineering-submittal milestone | Q85: Annex 3 Design and engineering package (railway) allocated by station hardware share | R85: 27 | S85: =R85/1000 | T85: 46390 | U85: 46399 | V85: 8
A86: SH-DES | B86: Design and engineering package (per railway, allocated to the station) | C86: ERY-E1020 | D86: Survey: SAR approval of survey report - Riyadh (Malaz) | E86: ENG.ERY.SRV.APR | F86: Engineering | G86: ERY | H86: MS3 | I86: 0.1 | J86: =Station_BOQ!R7 | K86: =I86*62000000*J86 | L86: 0.05 | M86: =ROUND(K86*L86,0) | N86: 15458 | O86: =N86-M86 | P86: MS3 SAR approval of engineering 10% x station price share 4.99% | Design stage key 5.0% of the SAR-approval milestone | Q86: Annex 3 Design and engineering package (railway) allocated by station hardware share | R86: 29 | S86: =R86/1000 | T86: 46400 | U86: 46420 | V86: 15
A87: SH-DES | B87: Design and engineering package (per railway, allocated to the station) | C87: ERY-E1030 | D87: Concept design: submittal - Riyadh (Malaz) | E87: ENG.ERY.CNC.SUB | F87: Engineering | G87: ERY | H87: MS2 | I87: 0.1 | J87: =Station_BOQ!R7 | K87: =I87*62000000*J87 | L87: 0.098 | M87: =ROUND(K87*L87,0) | N87: 30297 | O87: =N87-M87 | P87: MS2 Engineering submittal 10% x station price share 4.99% | Design stage key 9.8% of the engineering-submittal milestone | Q87: Annex 3 Design and engineering package (railway) allocated by station hardware share | R87: 20 | S87: =R87/1000 | T87: 46400 | U87: 46411 | V87: 8
A88: SH-DES | B88: Design and engineering package (per railway, allocated to the station) | C88: ERY-E1040 | D88: Concept design: SAR review and approval - Riyadh (Malaz) | E88: ENG.ERY.CNC.APR | F88: Engineering | G88: ERY | H88: MS3 | I88: 0.1 | J88: =Station_BOQ!R7 | K88: =I88*62000000*J88 | L88: 0.1 | M88: =ROUND(K88*L88,0) | N88: 30915 | O88: =N88-M88 | P88: MS3 SAR approval of engineering 10% x station price share 4.99% | Design stage key 10.0% of the SAR-approval milestone | Q88: Annex 3 Design and engineering package (railway) allocated by station hardware share | R88: 37 | S88: =R88/1000 | T88: 46412 | U88: 46432 | V88: 15
A89: SH-DES | B89: Design and engineering package (per railway, allocated to the station) | C89: ERY-E1050 | D89: Preliminary design: submittal - Riyadh (Malaz) | E89: ENG.ERY.PRE.SUB | F89: Engineering | G89: ERY | H89: MS2 | I89: 0.1 | J89: =Station_BOQ!R7 | K89: =I89*62000000*J89 | L89: 0.196 | M89: =ROUND(K89*L89,0) | N89: 60594 | O89: =N89-M89 | P89: MS2 Engineering submittal 10% x station price share 4.99% | Design stage key 19.6% of the engineering-submittal milestone | Q89: Annex 3 Design and engineering package (railway) allocated by station hardware share | R89: 49 | S89: =R89/1000 | T89: 46412 | U89: 46429 | V89: 14
A90: SH-DES | B90: Design and engineering package (per railway, allocated to the station) | C90: ERY-E1060 | D90: Preliminary design: SAR review and approval - Riyadh (Malaz) | E90: ENG.ERY.PRE.APR | F90: Engineering | G90: ERY | H90: MS3 | I90: 0.1 | J90: =Station_BOQ!R7 | K90: =I90*62000000*J90 | L90: 0.2 | M90: =ROUND(K90*L90,0) | N90: 61830 | O90: =N90-M90 | P90: MS3 SAR approval of engineering 10% x station price share 4.99% | Design stage key 20.0% of the SAR-approval milestone | Q90: Annex 3 Design and engineering package (railway) allocated by station hardware share | R90: 52 | S90: =R90/1000 | T90: 46432 | U90: 46460 | V90: 15
A91: SH-DES | B91: Design and engineering package (per railway, allocated to the station) | C91: ERY-E1070 | D91: Detailed design: submittal (drawings, BOQ, data sheets) - Riyadh (Malaz) | E91: ENG.ERY.DET.SUB | F91: Engineering | G91: ERY | H91: MS2 | I91: 0.1 | J91: =Station_BOQ!R7 | K91: =I91*62000000*J91 | L91: 0.392 | M91: =ROUND(K91*L91,0) | N91: 121188 | O91: =N91-M91 | P91: MS2 Engineering submittal 10% x station price share 4.99% | Design stage key 39.2% of the engineering-submittal milestone | Q91: Annex 3 Design and engineering package (railway) allocated by station hardware share | R91: 100 | S91: =R91/1000 | T91: 46432 | U91: 46469 | V91: 22
A92: SH-DES | B92: Design and engineering package (per railway, allocated to the station) | C92: ERY-E1080 | D92: Detailed design: SAR review and approval - Riyadh (Malaz) | E92: ENG.ERY.DET.APR | F92: Engineering | G92: ERY | H92: MS3 | I92: 0.1 | J92: =Station_BOQ!R7 | K92: =I92*62000000*J92 | L92: 0.4 | M92: =ROUND(K92*L92,0) | N92: 123661 | O92: =N92-M92 | P92: MS3 SAR approval of engineering 10% x station price share 4.99% | Design stage key 40.0% of the SAR-approval milestone | Q92: Annex 3 Design and engineering package (railway) allocated by station hardware share | R92: 68 | S92: =R92/1000 | T92: 46470 | U92: 46490 | V92: 15
A93: SH-DES | B93: Design and engineering package (per railway, allocated to the station) | C93: ERY-E1090 | D93: IFC and shop drawings: submittal - Riyadh (Malaz) | E93: ENG.ERY.IFC.SUB | F93: Engineering | G93: ERY | H93: MS2 | I93: 0.1 | J93: =Station_BOQ!R7 | K93: =I93*62000000*J93 | L93: 0.196 | M93: =ROUND(K93*L93,0) | N93: 60594 | O93: =N93-M93 | P93: MS2 Engineering submittal 10% x station price share 4.99% | Design stage key 19.6% of the engineering-submittal milestone | Q93: Annex 3 Design and engineering package (railway) allocated by station hardware share | R93: 45 | S93: =R93/1000 | T93: 46470 | U93: 46485 | V93: 12
A94: SH-DES | B94: Design and engineering package (per railway, allocated to the station) | C94: ERY-E1100 | D94: IFC and shop drawings: SAR approval and release - Riyadh (Malaz) | E94: ENG.ERY.IFC.APR | F94: Engineering | G94: ERY | H94: MS3 | I94: 0.1 | J94: =Station_BOQ!R7 | K94: =I94*62000000*J94 | L94: 0.2 | M94: =ROUND(K94*L94,0) | N94: 61830 | O94: =N94-M94 | P94: MS3 SAR approval of engineering 10% x station price share 4.99% | Design stage key 20.0% of the SAR-approval milestone | Q94: Annex 3 Design and engineering package (railway) allocated by station hardware share | R94: 56 | S94: =R94/1000 | T94: 46488 | U94: 46506 | V94: 15
A95: SH-DES | B95: Design and engineering package (per railway, allocated to the station) | C95: ERY-E1110 | D95: HCIS Stage 3 and 4 documents: preparation - Riyadh (Malaz) | E95: ENG.ERY.HCS.SUB | F95: Engineering | G95: ERY | H95: MS2 | I95: 0.1 | J95: =Station_BOQ!R7 | K95: =I95*62000000*J95 | L95: 0.049 | M95: =ROUND(K95*L95,0) | N95: 15148 | O95: =N95-M95 | P95: MS2 Engineering submittal 10% x station price share 4.99% | Design stage key 4.9% of the engineering-submittal milestone | Q95: Annex 3 Design and engineering package (railway) allocated by station hardware share | R95: 21 | S95: =R95/1000 | T95: 46443 | U95: 46485 | V95: 26
A96: SH-DES | B96: Design and engineering package (per railway, allocated to the station) | C96: ERY-E1120 | D96: HCIS Stage 3 and 4 documents: SAR final review and HCIS submission - Riyadh (Malaz) | E96: ENG.ERY.HCS.APR | F96: Engineering | G96: ERY | H96: MS3 | I96: 0.1 | J96: =Station_BOQ!R7 | K96: =I96*62000000*J96 | L96: 0.05 | M96: =ROUND(K96*L96,0) | N96: 15458 | O96: =N96-M96 | P96: MS3 SAR approval of engineering 10% x station price share 4.99% | Design stage key 5.0% of the SAR-approval milestone | Q96: Annex 3 Design and engineering package (railway) allocated by station hardware share | R96: 12 | S96: =R96/1000 | T96: 46488 | U96: 46506 | V96: 15
A97: SH-DES, SH-TRN | B97: Design and engineering package (per railway, allocated to the station) and Training (per railway, allocated): documentation and training share | C97: ERY-E1130 | D97: As-built and O&M documentation: submittal - Riyadh (Malaz) | E97: ENG.ERY.ASB.SUB | F97: Engineering | G97: ERY | H97: MS7 | I97: 0.1 | J97: =Station_BOQ!R7 | K97: =I97*62000000*J97 | L97: 0.15 | M97: =ROUND(K97*L97,0) | N97: 46373 | O97: =N97-M97 | P97: MS7 Final acceptance and handover 10% x station price share 4.99% | Fixed key 15% of final-acceptance milestone | Q97: Annex 3 documentation and training share | R97: 36 | S97: =R97/1000 | T97: 46679 | U97: 46715 | V97: 27
A98: SH-DES | B98: Design and engineering package (per railway, allocated to the station): documentation share | C98: ERY-E1140 | D98: As-built and O&M documentation: SAR review and approval - Riyadh (Malaz) | E98: ENG.ERY.ASB.APR | F98: Engineering | G98: ERY | H98: MS7 | I98: 0.1 | J98: =Station_BOQ!R7 | K98: =I98*62000000*J98 | L98: 0.05 | M98: =ROUND(K98*L98,0) | N98: 15458 | O98: =N98-M98 | P98: MS7 Final acceptance and handover 10% x station price share 4.99% | Fixed key 5% | Q98: Annex 3 documentation share | R98: 20 | S98: =R98/1000 | T98: 46716 | U98: 46736 | V98: 15
A99: - | B99: No BOQ cost: administrative or review step with no payment milestone | C99: ERY-X1010 | D99: Enabling works: site preparation, setting out, temporary works and utilities clearance - Riyadh (Malaz) | E99: CON.ERY.ENA | F99: Construction | G99: ERY | H99: MS5 | I99: 0.2 | J99: =Station_BOQ!R7 | K99: =I99*62000000*J99 | L99: 0.014237382 | M99: =ROUND(K99*L99,0) | N99: 8803 | O99: =N99-M99 | P99: MS5 Installation 20% x station price share 4.99% | BOQ civil share 35.6% x 4% (enabling: site preparation) | Q99: Annex 3 A6 Civil works (SAR 701,825) | R99: 48 | S99: =R99/1000 | T99: 46509 | U99: 46513 | V99: 5
A100: - | B100: No BOQ cost: administrative or review step with no payment milestone | C100: ERY-X1020 | D100: Enabling works: cable routes, duct-bank and cabinet plinth preparation - Riyadh (Malaz) | E100: CON.ERY.ENA | F100: Construction | G100: ERY | H100: MS5 | I100: 0.2 | J100: =Station_BOQ!R7 | K100: =I100*62000000*J100 | L100: 0.021356074 | M100: =ROUND(K100*L100,0) | N100: 13205 | O100: =N100-M100 | P100: MS5 Installation 20% x station price share 4.99% | BOQ civil share 35.6% x 6% (enabling: routes, ducts, plinths) | Q100: Annex 3 A6 Civil works (SAR 701,825) | R100: 72 | S100: =R100/1000 | T100: 46516 | U100: 46534 | V100: 10
A101: A1 | B101: A1 CCTV system | C101: ERY-P1010 | D101: Manufacture CCTV cameras and analytics - Riyadh (Malaz) | E101: PRO.ERY.CCT | F101: Procurement | G101: ERY | H101: MS4 | I101: 0.2 | J101: =Station_BOQ!R7 | K101: =I101*62000000*J101 | L101: 0.16349917 | M101: =ROUND(K101*L101,0) | N101: 101092 | O101: =N101-M101 | P101: MS4 Material delivery 20% x station price share 4.99% | BOQ section share 21.8% of station equipment x 75% (manufacture) | Q101: Annex 3 A1 CCTV system (SAR 276,849) | R101: 250 | S101: =R101/1000 | T101: 46509 | U101: 46574 | V101: 43
...

Sheet Distribution_Keys
A1: Distribution keys (cost within each payment milestone, and progress weights)
A3: Milestone | B3: Activity template | C3: Key | D3: Basis
A4: MS2 | B4: Survey, concept, preliminary, detailed, IFC, HCIS submittals | C4: 5 / 10 / 20 / 40 / 20 / 5 % of 98% | D4: Survey (including the permit follow-up) carries 7% of the MS2 bucket; design effort split by stage; the railway design and engineering package sits inside the station price
A5: MS3 | B5: Approval activities of the same six stages | C5: 5 / 10 / 20 / 40 / 20 / 5 % | D5: Mirror of the submittal key. Every SAR review is 21 days (15 working days)
A6: MS4 | B6: Manufacture CCTV, VMS, access control, UPS and network | C6: 75% split by BOQ section share | D6: A1, A2, A3 and A4+A5 shares of the station equipment value
A7: MS4 | B7: FAT / shipping and customs / delivery and receiving | C7: 5 / 15 / 5 % | D7: Fixed keys; spares and logistics sit inside delivery
A8: MS5 | B8: Enabling works / civil trenches and duct banks / poles and foundations | C8: 4 + 6 / 50 / 40 % of the A6 share | D8: A6 civil works share of station hardware; enabling works carved from the civil line
A9: MS5 | B9: Install cabinets / cabling / CCTV / VMS / access control | C9: 20 / 30 / 25 / 15 / 10 % of (1 - A6 share) | D9: Installation is included in the unit prices (Annex 3 works included)
A10: MS6 | B10: Pre-commissioning / SAT | C10: 40 / 60 % | D10: Fixed keys. Riyadh (Thumamah): 97% of the keys, 3% to the mock-up approval (no separate Annex 3 item)
A11: MS7 | B11: As-built submittal / approval / training / trial operation / handover | C11: 15 / 5 / 15 / 35 / 30 % | D11: Fixed keys
A12: MS1 | B12: Performance security / initial baseline / site establishment / mobilization submittals | C12: 15 / 10 / 45 / 30 % | D12: Project level, 20% of the total price
A15: EPC phase | B15: Component | C15: Weight (% of station progress) | D15: Basis
A16: Engineering | B16: Survey 8, concept 10, preliminary 18, detailed 30, IFC 18, HCIS 6, as-built 10 (of 12%); each stage split submittal / approval by duration | C16: 12 | D16: Typical EPC effort weighting for design
A17: Procurement | B17: Manufacture 24 (split by BOQ package share), FAT 4, shipping 8, delivery 4 | C17: 40 | D17: Procurement carries the largest share of a supply-led security contract
A18: Construction | B18: Enabling works 2.5, trenches 6.5, poles 5, cabinets 3, cabling 6, CCTV 5, VMS 3, access 2 | C18: 33 | D18: Site works
A19: Commissioning and handover | B19: Pre-commissioning 3, SAT 4, training 2, trial operation 3, handover 3 | C19: 15 | D19: Testing, trial and acceptance
A20: Total stations | C20: =SUM(C16:C19) | D20: Station weights sum to 100%
A22: Project level | B22: Mobilization and baseline 2.7% and closeout pack 1.3% of the whole project | C22: 4 | D22: Stations carry 96% of the project, each station weighted by its BOQ price share

Sheet S_Curve
A1: S-curve: cost (contract payment conditions) against progress (fair EPC distribution), spread linearly over each activity
A3: Month | B3: Cost in month (SAR) | C3: Cumulative cost (SAR) | D3: Cumulative cost % | E3: Progress in month % | F3: Cumulative progress %
A4: 46327 | B4: 10056396 | C4: =SUM(B$4:B4) | D4: =C4/62000000 | E4: 0.018348889 | F4: =SUM(E$4:E4)
A5: 46357 | B5: 2343599.5 | C5: =SUM(B$4:B5) | D5: =C5/62000000 | E5: 0.0036511111 | F5: =SUM(E$4:E5)
A6: 46388 | B6: 262431.14 | C6: =SUM(B$4:B6) | D6: =C6/62000000 | E6: 0.0070103619 | F6: =SUM(E$4:E6)
A7: 46419 | B7: 728474.66 | C7: =SUM(B$4:B7) | D7: =C7/62000000 | E7: 0.0074628639 | F7: =SUM(E$4:E7)
A8: 46447 | B8: 1149269 | C8: =SUM(B$4:B8) | D8: =C8/62000000 | E8: 0.0098651858 | F8: =SUM(E$4:E8)
A9: 46478 | B9: 1744434.9 | C9: =SUM(B$4:B9) | D9: =C9/62000000 | E9: 0.013752755 | F9: =SUM(E$4:E9)
A10: 46508 | B10: 1442176.6 | C10: =SUM(B$4:B10) | D10: =C10/62000000 | E10: 0.027052797 | F10: =SUM(E$4:E10)
A11: 46539 | B11: 1684819.1 | C11: =SUM(B$4:B11) | D11: =C11/62000000 | E11: 0.036512083 | F11: =SUM(E$4:E11)
A12: 46569 | B12: 1309023.7 | C12: =SUM(B$4:B12) | D12: =C12/62000000 | E12: 0.042003483 | F12: =SUM(E$4:E12)
A13: 46600 | B13: 1682555.5 | C13: =SUM(B$4:B13) | D13: =C13/62000000 | E13: 0.052617629 | F13: =SUM(E$4:E13)
A14: 46631 | B14: 1807538.7 | C14: =SUM(B$4:B14) | D14: =C14/62000000 | E14: 0.04574256 | F14: =SUM(E$4:E14)
A15: 46661 | B15: 1709705 | C15: =SUM(B$4:B15) | D15: =C15/62000000 | E15: 0.038601208 | F15: =SUM(E$4:E15)
... A38: 47362 | B38: 41713.773 | C38: =SUM(B$4:B38) | D38: =C38/62000000 | E38: 0.013656364 | F38: =SUM(E$4:E38)

Sheet Resources
A1: Resource ID | B1: Name | C1: Type | D1: Unit | E1: Price per unit | F1: Meaning | G1: How P6 uses it
A2: COST-SAR | B2: Contract cost (BOQ x payment milestones) | C2: Material | D2: SAR | E2: 0 | F2: Contract cost of the activity in SAR from the payment conditions applied to the BOQ station value (column N of BOQ_Mapping) | G2: Quantity carrier. Price 0, so it adds no budget cost. Set the price to 1 (and PROG-WT to 0) to see the contract-condition cost curve instead.
A3: PROG-WT | B3: Progress weight (fair EPC distribution, SAR value) | C3: Material | D3: SAR | E3: 1 | F3: Progress share x SAR 62,000,000 (100,000 points x SAR 620). Fair EPC distribution (see Distribution_Keys) | G3: Price 1, so budgeted cost = progress value in SAR. Activity % complete type is Physical, so earned value = physical % x this budget, and the cost and schedule performance indexes are measured in SAR on the progress distribution.

Sheet Activity_Codes
A1: Code type | B1: Code value | C1: Description | D1: Activities
A2: Area | B2: EWR | C2: EWR | D2: 164
A3: Area | B3: HHR | C3: HHR | D3: 164
A4: Area | B4: NSR | C4: NSR | D4: 248
A5: Area | B5: PRJ | C5: Project level | D5: 15
A6: Discipline | B6: ACC | C6: Access control and intercom | D6: 28
A7: Discipline | B7: CCTV | C7: CCTV system | D7: 42
A8: Discipline | B8: CIVIL | C8: Civil works | D8: 56
A9: Discipline | B9: DOCS | C9: Design documentation | D9: 224
A10: Discipline | B10: PM | C10: Project management and logistics | D10: 85
A11: Discipline | B11: TC | C11: Testing, commissioning and handover | D11: 100
A12: Discipline | B12: UPSNET | C12: UPS, network and cabinets | D12: 28
A13: Discipline | B13: VMS | C13: Video management and wall | D13: 28
... A73: Submittal or approval | B73: Submittal | C73: Submittal | D73: 101

Sheet WBS
A1: WBS code | B1: Name | C1: Level | D1: Parent
A2: 0580 | B2: 0580-Security Technology Salutation after eliminating Passenger Checking Roles | C2: 1
A3: PM | B3: Project Management and Mobilization | C3: 2 | D3: 0580
A4: ENG | B4: Engineering | C4: 2 | D4: 0580
A5: PRO | B5: Procurement | C5: 2 | D5: 0580
A6: CON | B6: Construction | C6: 2 | D6: 0580
A7: COM | B7: Commissioning and Handover | C7: 2 | D7: 0580
A8: PM.MOB | B8: Mobilization and baseline programme | C8: 3 | D8: PM
A9: PM.MST | B9: Contract milestones | C9: 3 | D9: PM
A10: PM.CLO | B10: Closeout | C10: 3 | D10: PM
A11: ENG.NRY | B11: Riyadh (Thumamah) (NSR) | C11: 3 | D11: ENG
A12: PRO.NRY | B12: Riyadh (Thumamah) (NSR) | C12: 3 | D12: PRO
A13: CON.NRY | B13: Riyadh (Thumamah) (NSR) | C13: 3 | D13: CON
A14: COM.NRY | B14: Riyadh (Thumamah) (NSR) | C14: 3 | D14: COM
... A515: COM.NQR.TOA | B515: Trial operation and acceptance | C515: 4 | D515: COM.NQR

Sheet Relationships
A1: Predecessor | B1: Successor | C1: Type | D1: Lag (work days)
A2: PRJ-M0000 | B2: PRJ-A1010 | C2: FS | D2: 0
A3: PRJ-M0000 | B3: PRJ-A1020 | C3: FS | D3: 0
A4: PRJ-A1020 | B4: PRJ-A1030 | C4: FS | D4: 0
A5: PRJ-M0000 | B5: PRJ-A1040 | C5: FS | D5: 5
A6: PRJ-M0000 | B6: PRJ-A1050 | C6: FS | D6: 5
A7: PRJ-M0000 | B7: PRJ-A1060 | C7: FS | D7: 0
A8: PRJ-A1010 | B8: PRJ-M1100 | C8: FS | D8: 0
A9: PRJ-A1030 | B9: PRJ-M1100 | C9: FS | D9: 0
A10: PRJ-A1040 | B10: PRJ-M1100 | C10: FS | D10: 0
A11: PRJ-A1050 | B11: PRJ-M1100 | C11: FS | D11: 0
A12: PRJ-M1100 | B12: PRJ-M1150 | C12: FS | D12: 0
A13: PRJ-M0000 | B13: PRJ-M1150 | C13: FS | D13: 45
... A913: PRJ-M0000 | B913: PRJ-MX99 | C913: FS | D913: 750

Sheet Invoicing_Monthly
A1: Invoices per month, detailed: each payment milestone is invoiced in the month its milestone activity is achieved in the programme
A2: Amount = clause 15 payment milestone x Annex 3 station price (formulas link to Payment_Milestones). Invoice month = month of the trigger milestone date. Payment terms after invoicing (days to pay) are not modelled.
A4: Invoice month | B4: Milestone date | C4: Milestone | D4: Description | E4: Station | F4: Railway | G4: Trigger activity ID | H4: Trigger activity | I4: Invoice amount (SAR) | J4: Cumulative (SAR) | K4: Cumulative %
A5: 46357 | B5: 46369 | C5: MS1 | D5: Mobilization | E5: All stations | F5: Project | G5: PRJ-M1100 | H5: MS1 Mobilization complete (payment milestone 20%) | I5: =Payment_Milestones!D5 | J5: =SUM(I$5:I5) | K5: =J5/62000000
A6: 46478 | B6: 46488 | C6: MS2 | D6: Engineering submittal | E6: Riyadh (Thumamah) (NRY) | F6: NSR | G6: NRY-E1200 | H6: MS2 Engineering submittal complete (10%) - Riyadh (Thumamah) | I6: =Payment_Milestones!C16 | J6: =SUM(I$5:I6) | K6: =J6/62000000
A7: 46478 | B7: 46488 | C7: MS2 | D7: Engineering submittal | E7: Makkah (HMK) | F7: HHR | G7: HMK-E1200 | H7: MS2 Engineering submittal complete (10%) - Makkah | I7: =Payment_Milestones!C17 | J7: =SUM(I$5:I7) | K7: =J7/62000000
A8: 46478 | B8: 46488 | C8: MS2 | D8: Engineering submittal | E8: Riyadh (Malaz) (ERY) | F8: EWR | G8: ERY-E1200 | H8: MS2 Engineering submittal complete (10%) - Riyadh (Malaz) | I8: =Payment_Milestones!C18 | J8: =SUM(I$5:I8) | K8: =J8/62000000
A9: 46508 | B9: 46509 | C9: MS3 | D9: SAR approval of engineering | E9: Riyadh (Thumamah) (NRY) | F9: NSR | G9: NRY-E1210 | H9: MS3 Engineering approved by SAR (10%) - Riyadh (Thumamah) | I9: =Payment_Milestones!D16 | J9: =SUM(I$5:I9) | K9: =J9/62000000
A10: 46508 | B10: 46509 | C10: MS3 | D10: SAR approval of engineering | E10: Makkah (HMK) | F10: HHR | G10: HMK-E1210 | H10: MS3 Engineering approved by SAR (10%) - Makkah | I10: =Payment_Milestones!D17 | J10: =SUM(I$5:I10) | K10: =J10/62000000
A11: 46508 | B11: 46509 | C11: MS3 | D11: SAR approval of engineering | E11: Riyadh (Malaz) (ERY) | F11: EWR | G11: ERY-E1210 | H11: MS3 Engineering approved by SAR (10%) - Riyadh (Malaz) | I11: =Payment_Milestones!D18 | J11: =SUM(I$5:I11) | K11: =J11/62000000
A12: 46539 | B12: 46544 | C12: MS2 | D12: Engineering submittal | E12: Jeddah (HJD) | F12: HHR | G12: HJD-E1200 | H12: MS2 Engineering submittal complete (10%) - Jeddah | I12: =Payment_Milestones!C19 | J12: =SUM(I$5:I12) | K12: =J12/62000000
A13: 46539 | B13: 46565 | C13: MS3 | D13: SAR approval of engineering | E13: Jeddah (HJD) | F13: HHR | G13: HJD-E1210 | H13: MS3 Engineering approved by SAR (10%) - Jeddah | I13: =Payment_Milestones!D19 | J13: =SUM(I$5:I13) | K13: =J13/62000000
A14: 46600 | B14: 46624 | C14: MS4 | D14: Material delivery | E14: Riyadh (Malaz) (ERY) | F14: EWR | G14: ERY-P1100 | H14: MS4 Material delivered (20%) - Riyadh (Malaz) | I14: =Payment_Milestones!E18 | J14: =SUM(I$5:I14) | K14: =J14/62000000
A15: 46631 | B15: 46632 | C15: MS4 | D15: Material delivery | E15: Riyadh (Thumamah) (NRY) | F15: NSR | G15: NRY-P1100 | H15: MS4 Material delivered (20%) - Riyadh (Thumamah) | I15: =Payment_Milestones!E16 | J15: =SUM(I$5:I15) | K15: =J15/62000000
A16: 46631 | B16: 46651 | C16: MS2 | D16: Engineering submittal | E16: Dammam (EDM) | F16: EWR | G16: EDM-E1200 | H16: MS2 Engineering submittal complete (10%) - Dammam | I16: =Payment_Milestones!C20 | J16: =SUM(I$5:I16) | K16: =J16/62000000
A17: 46661 | B17: 46673 | C17: MS3 | D17: SAR approval of engineering | E17: Dammam (EDM) | F17: EWR | G17: EDM-E1210 | H17: MS3 Engineering approved by SAR (10%) - Dammam | I17: =Payment_Milestones!D20 | J17: =SUM(I$5:I17) | K17: =J17/62000000
A18: 46661 | B18: 46679 | C18: MS5 | D18: Installation | E18: Riyadh (Malaz) (ERY) | F18: EWR | G18: ERY-C2100 | H18: MS5 Installation complete (20%) - Riyadh (Malaz) | I18: =Payment_Milestones!F18 | J18: =SUM(I$5:I18) | K18: =J18/62000000
A19: 46692 | B19: 46695 | C19: MS5 | D19: Installation | E19: Riyadh (Thumamah) (NRY) | F19: NSR | G19: NRY-C2100 | H19: MS5 Installation complete (20%) - Riyadh (Thumamah) | I19: =Payment_Milestones!F16 | J19: =SUM(I$5:I19) | K19: =J19/62000000
A20: 46692 | B20: 46695 | C20: MS6 | D20: Testing and commissioning (SAT) | E20: Riyadh (Malaz) (ERY) | F20: EWR | G20: ERY-T1100 | H20: MS6 SAT complete (10%) - Riyadh (Malaz) | I20: =Payment_Milestones!G18 | J20: =SUM(I$5:I20) | K20: =J20/62000000
A21: 46692 | B21: 46700 | C21: MS4 | D21: Material delivery | E21: Makkah (HMK) | F21: HHR | G21: HMK-P1100 | H21: MS4 Material delivered (20%) - Makkah | I21: =Payment_Milestones!E17 | J21: =SUM(I$5:I21) | K21: =J21/62000000
A22: 46692 | B22: 46705 | C22: MS2 | D22: Engineering submittal | E22: Al Qassim (NQS) | F22: NSR | G22: NQS-E1200 | H22: MS2 Engineering submittal complete (10%) - Al Qassim | I22: =Payment_Milestones!C21 | J22: =SUM(I$5:I22) | K22: =J22/62000000
A23: 46692 | B23: 46705 | C23: MS2 | D23: Engineering submittal | E23: Hufuf (EHF) | F23: EWR | G23: EHF-E1200 | H23: MS2 Engineering submittal complete (10%) - Hufuf | I23: =Payment_Milestones!C22 | J23: =SUM(I$5:I23) | K23: =J23/62000000
A24: 46722 | B24: 46726 | C24: MS3 | D24: SAR approval of engineering | E24: Al Qassim (NQS) | F24: NSR | G24: NQS-E1210 | H24: MS3 Engineering approved by SAR (10%) - Al Qassim | I24: =Payment_Milestones!D21 | J24: =SUM(I$5:I24) | K24: =J24/62000000
A25: 46722 | B25: 46726 | C25: MS3 | D25: SAR approval of engineering | E25: Hufuf (EHF) | F25: EWR | G25: EHF-E1210 | H25: MS3 Engineering approved by SAR (10%) - Hufuf | I25: =Payment_Milestones!D22 | J25: =SUM(I$5:I25) | K25: =J25/62000000
A26: 46722 | B26: 46727 | C26: MS6 | D26: Testing and commissioning (SAT) | E26: Riyadh (Thumamah) (NRY) | F26: NSR | G26: NRY-T1100 | H26: MS6 SAT complete (10%) - Riyadh (Thumamah) | I26: =Payment_Milestones!G16 | J26: =SUM(I$5:I26) | K26: =J26/62000000
A27: 46722 | B27: 46748 | C27: MS4 | D27: Material delivery | E27: Jeddah (HJD) | F27: HHR | G27: HJD-P1100 | H27: MS4 Material delivered (20%) - Jeddah | I27: =Payment_Milestones!E19 | J27: =SUM(I$5:I27) | K27: =J27/62000000
A28: 46722 | B28: 46751 | C28: MS2 | D28: Engineering submittal | E28: Al Majma'ah (NMJ) | F28: NSR | G28: NMJ-E1200 | H28: MS2 Engineering submittal complete (10%) - Al Majma'ah | I28: =Payment_Milestones!C23 | J28: =SUM(I$5:I28) | K28: =J28/62000000
A29: 46753 | B29: 46769 | C29: MS7 | D29: Final acceptance and handover | E29: Riyadh (Malaz) (ERY) | F29: EWR | G29: ERY-T3100 | H29: MS7 Station accepted - final acceptance and handover (10%) - Riyadh (Malaz) | I29: =Payment_Milestones!H18 | J29: =SUM(I$5:I29) | K29: =J29/62000000
A30: 46753 | B30: 46772 | C30: MS3 | D30: SAR approval of engineering | E30: Al Majma'ah (NMJ) | F30: NSR | G30: NMJ-E1210 | H30: MS3 Engineering approved by SAR (10%) - Al Majma'ah | I30: =Payment_Milestones!D23 | J30: =SUM(I$5:I30) | K30: =J30/62000000
A31: 46753 | B31: 46783 | C31: MS4 | D31: Material delivery | E31: Dammam (EDM) | F31: EWR | G31: EDM-P1100 | H31: MS4 Material delivered (20%) - Dammam | I31: =Payment_Milestones!E20 | J31: =SUM(I$5:I31) | K31: =J31/62000000
A32: 46784 | B32: 46786 | C32: MS7 | D32: Final acceptance and handover | E32: Riyadh (Thumamah) (NRY) | F32: NSR | G32: NRY-T3100 | H32: MS7 Station accepted - final acceptance and handover (10%) - Riyadh (Thumamah) | I32: =Payment_Milestones!H16 | J32: =SUM(I$5:I32) | K32: =J32/62000000
A33: 46813 | B33: 46820 | C33: MS5 | D33: Installation | E33: Makkah (HMK) | F33: HHR | G33: HMK-C2100 | H33: MS5 Installation complete (20%) - Makkah | I33: =Payment_Milestones!F17 | J33: =SUM(I$5:I33) | K33: =J33/62000000
A34: 46813 | B34: 46839 | C34: MS4 | D34: Material delivery | E34: Hufuf (EHF) | F34: EWR | G34: EHF-P1100 | H34: MS4 Material delivered (20%) - Hufuf | I34: =Payment_Milestones!E22 | J34: =SUM(I$5:I34) | K34: =J34/62000000
A35: 46813 | B35: 46842 | C35: MS5 | D35: Installation | E35: Dammam (EDM) | F35: EWR | G35: EDM-C2100 | H35: MS5 Installation complete (20%) - Dammam | I35: =Payment_Milestones!F20 | J35: =SUM(I$5:I35) | K35: =J35/62000000
A36: 46844 | B36: 46849 | C36: MS4 | D36: Material delivery | E36: Al Qassim (NQS) | F36: NSR | G36: NQS-P1100 | H36: MS4 Material delivered (20%) - Al Qassim | I36: =Payment_Milestones!E21 | J36: =SUM(I$5:I36) | K36: =J36/62000000
A37: 46844 | B37: 46849 | C37: MS5 | D37: Installation | E37: Jeddah (HJD) | F37: HHR | G37: HJD-C2100 | H37: MS5 Installation complete (20%) - Jeddah | I37: =Payment_Milestones!F19 | J37: =SUM(I$5:I37) | K37: =J37/62000000
A38: 46844 | B38: 46860 | C38: MS6 | D38: Testing and commissioning (SAT) | E38: Dammam (EDM) | F38: EWR | G38: EDM-T1100 | H38: MS6 SAT complete (10%) - Dammam | I38: =Payment_Milestones!G20 | J38: =SUM(I$5:I38) | K38: =J38/62000000
A39: 46844 | B39: 46861 | C39: MS2 | D39: Engineering submittal | E39: KAEC (HKA) | F39: HHR | G39: HKA-E1200 | H39: MS2 Engineering submittal complete (10%) - KAEC | I39: =Payment_Milestones!C24 | J39: =SUM(I$5:I39) | K39: =J39/62000000
A40: 46844 | B40: 46861 | C40: MS2 | D40: Engineering submittal | E40: Madinah (HMD) | F40: HHR | G40: HMD-E1200 | H40: MS2 Engineering submittal complete (10%) - Madinah | I40: =Payment_Milestones!C25 | J40: =SUM(I$5:I40) | K40: =J40/62000000
A41: 46844 | B41: 46862 | C41: MS6 | D41: Testing and commissioning (SAT) | E41: Makkah (HMK) | F41: HHR | G41: HMK-T1100 | H41: MS6 SAT complete (10%) - Makkah | I41: =Payment_Milestones!G17 | J41: =SUM(I$5:I41) | K41: =J41/62000000
A42: 46874 | B42: 46889 | C42: MS3 | D42: SAR approval of engineering | E42: KAEC (HKA) | F42: HHR | G42: HKA-E1210 | H42: MS3 Engineering approved by SAR (10%) - KAEC | I42: =Payment_Milestones!D24 | J42: =SUM(I$5:I42) | K42: =J42/62000000
A43: 46874 | B43: 46889 | C43: MS3 | D43: SAR approval of engineering | E43: Madinah (HMD) | F43: HHR | G43: HMD-E1210 | H43: MS3 Engineering approved by SAR (10%) - Madinah | I43: =Payment_Milestones!D25 | J43: =SUM(I$5:I43) | K43: =J43/62000000
A44: 46874 | B44: 46894 | C44: MS6 | D44: Testing and commissioning (SAT) | E44: Jeddah (HJD) | F44: HHR | G44: HJD-T1100 | H44: MS6 SAT complete (10%) - Jeddah | I44: =Payment_Milestones!G19 | J44: =SUM(I$5:I44) | K44: =J44/62000000
A45: 46874 | B45: 46896 | C45: MS5 | D45: Installation | E45: Hufuf (EHF) | F45: EWR | G45: EHF-C2100 | H45: MS5 Installation complete (20%) - Hufuf | I45: =Payment_Milestones!F22 | J45: =SUM(I$5:I45) | K45: =J45/62000000
A46: 46874 | B46: 46904 | C46: MS4 | D46: Material delivery | E46: Al Majma'ah (NMJ) | F46: NSR | G46: NMJ-P1100 | H46: MS4 Material delivered (20%) - Al Majma'ah | I46: =Payment_Milestones!E23 | J46: =SUM(I$5:I46) | K46: =J46/62000000
A47: 46905 | B47: 46912 | C47: MS6 | D47: Testing and commissioning (SAT) | E47: Hufuf (EHF) | F47: EWR | G47: EHF-T1100 | H47: MS6 SAT complete (10%) - Hufuf | I47: =Payment_Milestones!G22 | J47: =SUM(I$5:I47) | K47: =J47/62000000
A48: 46905 | B48: 46918 | C48: MS5 | D48: Installation | E48: Al Qassim (NQS) | F48: NSR | G48: NQS-C2100 | H48: MS5 Installation complete (20%) - Al Qassim | I48: =Payment_Milestones!F21 | J48: =SUM(I$5:I48) | K48: =J48/62000000
A49: 46905 | B49: 46922 | C49: MS2 | D49: Engineering submittal | E49: Abqaiq (EAB) | F49: EWR | G49: EAB-E1200 | H49: MS2 Engineering submittal complete (10%) - Abqaiq | I49: =Payment_Milestones!C26 | J49: =SUM(I$5:I49) | K49: =J49/62000000
A50: 46935 | B50: 46937 | C50: MS6 | D50: Testing and commissioning (SAT) | E50: Al Qassim (NQS) | F50: NSR | G50: NQS-T1100 | H50: MS6 SAT complete (10%) - Al Qassim | I50: =Payment_Milestones!G21 | J50: =SUM(I$5:I50) | K50: =J50/62000000
A51: 46935 | B51: 46939 | C51: MS7 | D51: Final acceptance and handover | E51: Dammam (EDM) | F51: EWR | G51: EDM-T3100 | H51: MS7 Station accepted - final acceptance and handover (10%) - Dammam | I51: =Payment_Milestones!H20 | J51: =SUM(I$5:I51) | K51: =J51/62000000
A52: 46935 | B52: 46943 | C52: MS3 | D52: SAR approval of engineering | E52: Abqaiq (EAB) | F52: EWR | G52: EAB-E1210 | H52: MS3 Engineering approved by SAR (10%) - Abqaiq | I52: =Payment_Milestones!D26 | J52: =SUM(I$5:I52) | K52: =J52/62000000
A53: 46935 | B53: 46943 | C53: MS7 | D53: Final acceptance and handover | E53: Makkah (HMK) | F53: HHR | G53: HMK-T3100 | H53: MS7 Station accepted - final acceptance and handover (10%) - Makkah | I53: =Payment_Milestones!H17 | J53: =SUM(I$5:I53) | K53: =J53/62000000
A54: 46935 | B54: 46946 | C54: MS2 | D54: Engineering submittal | E54: Hail (NHL) | F54: NSR | G54: NHL-E1200 | H54: MS2 Engineering submittal complete (10%) - Hail | I54: =Payment_Milestones!C27 | J54: =SUM(I$5:I54) | K54: =J54/62000000
A55: 46966 | B55: 46966 | C55: MS5 | D55: Installation | E55: Al Majma'ah (NMJ) | F55: NSR | G55: NMJ-C2100 | H55: MS5 Installation complete (20%) - Al Majma'ah | I55: =Payment_Milestones!F23 | J55: =SUM(I$5:I55) | K55: =J55/62000000
A56: 46966 | B56: 46966 | C56: MS7 | D56: Final acceptance and handover | E56: Jeddah (HJD) | F56: HHR | G56: HJD-T3100 | H56: MS7 Station accepted - final acceptance and handover (10%) - Jeddah | I56: =Payment_Milestones!H19 | J56: =SUM(I$5:I56) | K56: =J56/62000000
A57: 46966 | B57: 46967 | C57: MS3 | D57: SAR approval of engineering | E57: Hail (NHL) | F57: NSR | G57: NHL-E1210 | H57: MS3 Engineering approved by SAR (10%) - Hail | I57: =Payment_Milestones!D27 | J57: =SUM(I$5:I57) | K57: =J57/62000000
A58: 46966 | B58: 46985 | C58: MS6 | D58: Testing and commissioning (SAT) | E58: Al Majma'ah (NMJ) | F58: NSR | G58: NMJ-T1100 | H58: MS6 SAT complete (10%) - Al Majma'ah | I58: =Payment_Milestones!G23 | J58: =SUM(I$5:I58) | K58: =J58/62000000
A59: 46966 | B59: 46986 | C59: MS7 | D59: Final acceptance and handover | E59: Hufuf (EHF) | F59: EWR | G59: EHF-T3100 | H59: MS7 Station accepted - final acceptance and handover (10%) - Hufuf | I59: =Payment_Milestones!H22 | J59: =SUM(I$5:I59) | K59: =J59/62000000
A60: 46997 | B60: 47009 | C60: MS7 | D60: Final acceptance and handover | E60: Al Qassim (NQS) | F60: NSR | G60: NQS-T3100 | H60: MS7 Station accepted - final acceptance and handover (10%) - Al Qassim | I60: =Payment_Milestones!H21 | J60: =SUM(I$5:I60) | K60: =J60/62000000
A61: 46997 | B61: 47023 | C61: MS2 | D61: Engineering submittal | E61: Al Jouf (NJF) | F61: NSR | G61: NJF-E1200 | H61: MS2 Engineering submittal complete (10%) - Al Jouf | I61: =Payment_Milestones!C28 | J61: =SUM(I$5:I61) | K61: =J61/62000000
A62: 47027 | B62: 47030 | C62: MS4 | D62: Material delivery | E62: Madinah (HMD) | F62: HHR | G62: HMD-P1100 | H62: MS4 Material delivered (20%) - Madinah | I62: =Payment_Milestones!E25 | J62: =SUM(I$5:I62) | K62: =J62/62000000
A63: 47027 | B63: 47031 | C63: MS4 | D63: Material delivery | E63: KAEC (HKA) | F63: HHR | G63: HKA-P1100 | H63: MS4 Material delivered (20%) - KAEC | I63: =Payment_Milestones!E24 | J63: =SUM(I$5:I63) | K63: =J63/62000000
A64: 47027 | B64: 47044 | C64: MS3 | D64: SAR approval of engineering | E64: Al Jouf (NJF) | F64: NSR | G64: NJF-E1210 | H64: MS3 Engineering approved by SAR (10%) - Al Jouf | I64: =Payment_Milestones!D28 | J64: =SUM(I$5:I64) | K64: =J64/62000000
A65: 47027 | B65: 47044 | C65: MS4 | D65: Material delivery | E65: Abqaiq (EAB) | F65: EWR | G65: EAB-P1100 | H65: MS4 Material delivered (20%) - Abqaiq | I65: =Payment_Milestones!E26 | J65: =SUM(I$5:I65) | K65: =J65/62000000
A66: 47027 | B66: 47057 | C66: MS7 | D66: Final acceptance and handover | E66: Al Majma'ah (NMJ) | F66: NSR | G66: NMJ-T3100 | H66: MS7 Station accepted - final acceptance and handover (10%) - Al Majma'ah | I66: =Payment_Milestones!H23 | J66: =SUM(I$5:I66) | K66: =J66/62000000
A67: 47058 | B67: 47069 | C67: MS2 | D67: Engineering submittal | E67: Al Qurayyat (NQR) | F67: NSR | G67: NQR-E1200 | H67: MS2 Engineering submittal complete (10%) - Al Qurayyat | I67: =Payment_Milestones!C29 | J67: =SUM(I$5:I67) | K67: =J67/62000000
A68: 47058 | B68: 47080 | C68: MS5 | D68: Installation | E68: Abqaiq (EAB) | F68: EWR | G68: EAB-C2100 | H68: MS5 Installation complete (20%) - Abqaiq | I68: =Payment_Milestones!F26 | J68: =SUM(I$5:I68) | K68: =J68/62000000
A69: 47058 | B69: 47085 | C69: MS4 | D69: Material delivery | E69: Hail (NHL) | F69: NSR | G69: NHL-P1100 | H69: MS4 Material delivered (20%) - Hail | I69: =Payment_Milestones!E27 | J69: =SUM(I$5:I69) | K69: =J69/62000000
A70: 47088 | B70: 47090 | C70: MS3 | D70: SAR approval of engineering | E70: Al Qurayyat (NQR) | F70: NSR | G70: NQR-E1210 | H70: MS3 Engineering approved by SAR (10%) - Al Qurayyat | I70: =Payment_Milestones!D29 | J70: =SUM(I$5:I70) | K70: =J70/62000000
A71: 47088 | B71: 47097 | C71: MS6 | D71: Testing and commissioning (SAT) | E71: Abqaiq (EAB) | F71: EWR | G71: EAB-T1100 | H71: MS6 SAT complete (10%) - Abqaiq | I71: =Payment_Milestones!G26 | J71: =SUM(I$5:I71) | K71: =J71/62000000
A72: 47119 | B72: 47127 | C72: MS5 | D72: Installation | E72: KAEC (HKA) | F72: HHR | G72: HKA-C2100 | H72: MS5 Installation complete (20%) - KAEC | I72: =Payment_Milestones!F24 | J72: =SUM(I$5:I72) | K72: =J72/62000000
A73: 47119 | B73: 47132 | C73: MS5 | D73: Installation | E73: Madinah (HMD) | F73: HHR | G73: HMD-C2100 | H73: MS5 Installation complete (20%) - Madinah | I73: =Payment_Milestones!F25 | J73: =SUM(I$5:I73) | K73: =J73/62000000
A74: 47119 | B74: 47147 | C74: MS5 | D74: Installation | E74: Hail (NHL) | F74: NSR | G74: NHL-C2100 | H74: MS5 Installation complete (20%) - Hail | I74: =Payment_Milestones!F27 | J74: =SUM(I$5:I74) | K74: =J74/62000000
A75: 47150 | B75: 47155 | C75: MS6 | D75: Testing and commissioning (SAT) | E75: KAEC (HKA) | F75: HHR | G75: HKA-T1100 | H75: MS6 SAT complete (10%) - KAEC | I75: =Payment_Milestones!G24 | J75: =SUM(I$5:I75) | K75: =J75/62000000
A76: 47150 | B76: 47168 | C76: MS6 | D76: Testing and commissioning (SAT) | E76: Madinah (HMD) | F76: HHR | G76: HMD-T1100 | H76: MS6 SAT complete (10%) - Madinah | I76: =Payment_Milestones!G25 | J76: =SUM(I$5:I76) | K76: =J76/62000000
A77: 47150 | B77: 47169 | C77: MS4 | D77: Material delivery | E77: Al Jouf (NJF) | F77: NSR | G77: NJF-P1100 | H77: MS4 Material delivered (20%) - Al Jouf | I77: =Payment_Milestones!E28 | J77: =SUM(I$5:I77) | K77: =J77/62000000
A78: 47150 | B78: 47174 | C78: MS6 | D78: Testing and commissioning (SAT) | E78: Hail (NHL) | F78: NSR | G78: NHL-T1100 | H78: MS6 SAT complete (10%) - Hail | I78: =Payment_Milestones!G27 | J78: =SUM(I$5:I78) | K78: =J78/62000000
A79: 47150 | B79: 47177 | C79: MS7 | D79: Final acceptance and handover | E79: Abqaiq (EAB) | F79: EWR | G79: EAB-T3100 | H79: MS7 Station accepted - final acceptance and handover (10%) - Abqaiq | I79: =Payment_Milestones!H26 | J79: =SUM(I$5:I79) | K79: =J79/62000000
A80: 47209 | B80: 47216 | C80: MS4 | D80: Material delivery | E80: Al Qurayyat (NQR) | F80: NSR | G80: NQR-P1100 | H80: MS4 Material delivered (20%) - Al Qurayyat | I80: =Payment_Milestones!E29 | J80: =SUM(I$5:I80) | K80: =J80/62000000
A81: 47239 | B81: 47239 | C81: MS5 | D81: Installation | E81: Al Jouf (NJF) | F81: NSR | G81: NJF-C2100 | H81: MS5 Installation complete (20%) - Al Jouf | I81: =Payment_Milestones!F28 | J81: =SUM(I$5:I81) | K81: =J81/62000000
A82: 47239 | B82: 47244 | C82: MS7 | D82: Final acceptance and handover | E82: KAEC (HKA) | F82: HHR | G82: HKA-T3100 | H82: MS7 Station accepted - final acceptance and handover (10%) - KAEC | I82: =Payment_Milestones!H24 | J82: =SUM(I$5:I82) | K82: =J82/62000000
A83: 47239 | B83: 47248 | C83: MS7 | D83: Final acceptance and handover | E83: Madinah (HMD) | F83: HHR | G83: HMD-T3100 | H83: MS7 Station accepted - final acceptance and handover (10%) - Madinah | I83: =Payment_Milestones!H25 | J83: =SUM(I$5:I83) | K83: =J83/62000000
A84: 47239 | B84: 47253 | C84: MS7 | D84: Final acceptance and handover | E84: Hail (NHL) | F84: NSR | G84: NHL-T3100 | H84: MS7 Station accepted - final acceptance and handover (10%) - Hail | I84: =Payment_Milestones!H27 | J84: =SUM(I$5:I84) | K84: =J84/62000000
A85: 47239 | B85: 47258 | C85: MS6 | D85: Testing and commissioning (SAT) | E85: Al Jouf (NJF) | F85: NSR | G85: NJF-T1100 | H85: MS6 SAT complete (10%) - Al Jouf | I85: =Payment_Milestones!G28 | J85: =SUM(I$5:I85) | K85: =J85/62000000
A86: 47270 | B86: 47283 | C86: MS5 | D86: Installation | E86: Al Qurayyat (NQR) | F86: NSR | G86: NQR-C2100 | H86: MS5 Installation complete (20%) - Al Qurayyat | I86: =Payment_Milestones!F29 | J86: =SUM(I$5:I86) | K86: =J86/62000000
A87: 47300 | B87: 47302 | C87: MS6 | D87: Testing and commissioning (SAT) | E87: Al Qurayyat (NQR) | F87: NSR | G87: NQR-T1100 | H87: MS6 SAT complete (10%) - Al Qurayyat | I87: =Payment_Milestones!G29 | J87: =SUM(I$5:I87) | K87: =J87/62000000
A88: 47300 | B88: 47330 | C88: MS7 | D88: Final acceptance and handover | E88: Al Jouf (NJF) | F88: NSR | G88: NJF-T3100 | H88: MS7 Station accepted - final acceptance and handover (10%) - Al Jouf | I88: =Payment_Milestones!H28 | J88: =SUM(I$5:I88) | K88: =J88/62000000
A89: 47362 | B89: 47374 | C89: MS7 | D89: Final acceptance and handover | E89: Al Qurayyat (NQR) | F89: NSR | G89: NQR-T3100 | H89: MS7 Station accepted - final acceptance and handover (10%) - Al Qurayyat | I89: =Payment_Milestones!H29 | J89: =SUM(I$5:I89) | K89: =J89/62000000
A90: Total | I90: =SUM(I5:I89)
H91: Difference to contract price (should be 0) | I91: =I90-62000000
A93: Monthly invoicing by payment milestone
A94: Month | B94: MS1 | C94: MS2 | D94: MS3 | E94: MS4 | F94: MS5 | G94: MS6 | H94: MS7 | I94: Invoiced in month (SAR) | J94: Cumulative invoiced (SAR) | K94: Cumulative %
A95: 46327 | B95: =SUMIFS($I$5:$I$89,$A$5:$A$89,$A95,$C$5:$C$89,B$94) | C95: =SUMIFS($I$5:$I$89,$A$5:$A$89,$A95,$C$5:$C$89,C$94) | D95: =SUMIFS($I$5:$I$89,$A$5:$A$89,$A95,$C$5:$C$89,D$94) | E95: =SUMIFS($I$5:$I$89,$A$5:$A$89,$A95,$C$5:$C$89,E$94) | F95: =SUMIFS($I$5:$I$89,$A$5:$A$89,$A95,$C$5:$C$89,F$94) | G95: =SUMIFS($I$5:$I$89,$A$5:$A$89,$A95,$C$5:$C$89,G$94) | H95: =SUMIFS($I$5:$I$89,$A$5:$A$89,$A95,$C$5:$C$89,H$94) | I95: =SUM(B95:H95) | J95: =SUM(I$95:I95) | K95: =J95/62000000
A96: 46357 | B96: =SUMIFS($I$5:$I$89,$A$5:$A$89,$A96,$C$5:$C$89,B$94) | C96: =SUMIFS($I$5:$I$89,$A$5:$A$89,$A96,$C$5:$C$89,C$94) | D96: =SUMIFS($I$5:$I$89,$A$5:$A$89,$A96,$C$5:$C$89,D$94) | E96: =SUMIFS($I$5:$I$89,$A$5:$A$89,$A96,$C$5:$C$89,E$94) | F96: =SUMIFS($I$5:$I$89,$A$5:$A$89,$A96,$C$5:$C$89,F$94) | G96: =SUMIFS($I$5:$I$89,$A$5:$A$89,$A96,$C$5:$C$89,G$94) | H96: =SUMIFS($I$5:$I$89,$A$5:$A$89,$A96,$C$5:$C$89,H$94) | I96: =SUM(B96:H96) | J96: =SUM(I$95:I96) | K96: =J96/62000000
A97: 46388 | B97: =SUMIFS($I$5:$I$89,$A$5:$A$89,$A97,$C$5:$C$89,B$94) | C97: =SUMIFS($I$5:$I$89,$A$5:$A$89,$A97,$C$5:$C$89,C$94) | D97: =SUMIFS($I$5:$I$89,$A$5:$A$89,$A97,$C$5:$C$89,D$94) | E97: =SUMIFS($I$5:$I$89,$A$5:$A$89,$A97,$C$5:$C$89,E$94) | F97: =SUMIFS($I$5:$I$89,$A$5:$A$89,$A97,$C$5:$C$89,F$94) | G97: =SUMIFS($I$5:$I$89,$A$5:$A$89,$A97,$C$5:$C$89,G$94) | H97: =SUMIFS($I$5:$I$89,$A$5:$A$89,$A97,$C$5:$C$89,H$94) | I97: =SUM(B97:H97) | J97: =SUM(I$95:I97) | K97: =J97/62000000
A98: 46419 | B98: =SUMIFS($I$5:$I$89,$A$5:$A$89,$A98,$C$5:$C$89,B$94) | C98: =SUMIFS($I$5:$I$89,$A$5:$A$89,$A98,$C$5:$C$89,C$94) | D98: =SUMIFS($I$5:$I$89,$A$5:$A$89,$A98,$C$5:$C$89,D$94) | E98: =SUMIFS($I$5:$I$89,$A$5:$A$89,$A98,$C$5:$C$89,E$94) | F98: =SUMIFS($I$5:$I$89,$A$5:$A$89,$A98,$C$5:$C$89,F$94) | G98: =SUMIFS($I$5:$I$89,$A$5:$A$89,$A98,$C$5:$C$89,G$94) | H98: =SUMIFS($I$5:$I$89,$A$5:$A$89,$A98,$C$5:$C$89,H$94) | I98: =SUM(B98:H98) | J98: =SUM(I$95:I98) | K98: =J98/62000000
A99: 46447 | B99: =SUMIFS($I$5:$I$89,$A$5:$A$89,$A99,$C$5:$C$89,B$94) | C99: =SUMIFS($I$5:$I$89,$A$5:$A$89,$A99,$C$5:$C$89,C$94) | D99: =SUMIFS($I$5:$I$89,$A$5:$A$89,$A99,$C$5:$C$89,D$94) | E99: =SUMIFS($I$5:$I$89,$A$5:$A$89,$A99,$C$5:$C$89,E$94) | F99: =SUMIFS($I$5:$I$89,$A$5:$A$89,$A99,$C$5:$C$89,F$94) | G99: =SUMIFS($I$5:$I$89,$A$5:$A$89,$A99,$C$5:$C$89,G$94) | H99: =SUMIFS($I$5:$I$89,$A$5:$A$89,$A99,$C$5:$C$89,H$94) | I99: =SUM(B99:H99) | J99: =SUM(I$95:I99) | K99: =J99/62000000
A100: 46478 | B100: =SUMIFS($I$5:$I$89,$A$5:$A$89,$A100,$C$5:$C$89,B$94) | C100: =SUMIFS($I$5:$I$89,$A$5:$A$89,$A100,$C$5:$C$89,C$94) | D100: =SUMIFS($I$5:$I$89,$A$5:$A$89,$A100,$C$5:$C$89,D$94) | E100: =SUMIFS($I$5:$I$89,$A$5:$A$89,$A100,$C$5:$C$89,E$94) | F100: =SUMIFS($I$5:$I$89,$A$5:$A$89,$A100,$C$5:$C$89,F$94) | G100: =SUMIFS($I$5:$I$89,$A$5:$A$89,$A100,$C$5:$C$89,G$94) | H100: =SUMIFS($I$5:$I$89,$A$5:$A$89,$A100,$C$5:$C$89,H$94) | I100: =SUM(B100:H100) | J100: =SUM(I$95:I100) | K100: =J100/62000000
A101: 46508 | B101: =SUMIFS($I$5:$I$89,$A$5:$A$89,$A101,$C$5:$C$89,B$94) | C101: =SUMIFS($I$5:$I$89,$A$5:$A$89,$A101,$C$5:$C$89,C$94) | D101: =SUMIFS($I$5:$I$89,$A$5:$A$89,$A101,$C$5:$C$89,D$94) | E101: =SUMIFS($I$5:$I$89,$A$5:$A$89,$A101,$C$5:$C$89,E$94) | F101: =SUMIFS($I$5:$I$89,$A$5:$A$89,$A101,$C$5:$C$89,F$94) | G101: =SUMIFS($I$5:$I$89,$A$5:$A$89,$A101,$C$5:$C$89,G$94) | H101: =SUMIFS($I$5:$I$89,$A$5:$A$89,$A101,$C$5:$C$89,H$94) | I101: =SUM(B101:H101) | J101: =SUM(I$95:I101) | K101: =J101/62000000
A102: 46539 | B102: =SUMIFS($I$5:$I$89,$A$5:$A$89,$A102,$C$5:$C$89,B$94) | C102: =SUMIFS($I$5:$I$89,$A$5:$A$89,$A102,$C$5:$C$89,C$94) | D102: =SUMIFS($I$5:$I$89,$A$5:$A$89,$A102,$C$5:$C$89,D$94) | E102: =SUMIFS($I$5:$I$89,$A$5:$A$89,$A102,$C$5:$C$89,E$94) | F102: =SUMIFS($I$5:$I$89,$A$5:$A$89,$A102,$C$5:$C$89,F$94) | G102: =SUMIFS($I$5:$I$89,$A$5:$A$89,$A102,$C$5:$C$89,G$94) | H102: =SUMIFS($I$5:$I$89,$A$5:$A$89,$A102,$C$5:$C$89,H$94) | I102: =SUM(B102:H102) | J102: =SUM(I$95:I102) | K102: =J102/62000000
...
